{
	"title": "The St. Valentine's Day Massacre",
	"_year_data": "1967",
	"year": 1967,
	"rated": "Not Rated",
	"released": "1967-06-29T12:00:00.000Z",
	"runtime": "100 min",
	"genres": "Crime, Drama, History",
	"director": "Roger Corman",
	"writer": "Howard Browne",
	"actors": "Jason Robards, George Segal, Ralph Meeker, Jean Hale",
	"plot": "Chicago February 14th 1929. Al Capone finally establishes himself as the city's boss of organised crime. In a north-side garage his hoods, dressed as policemen, surprise and mow down with machine-guns the key members of Bugs Moran's rival gang. The film traces the history of the incident, and the lives affected and in some cases ended by it.",
	"languages": "English, Italian",
	"country": "USA",
	"awards": "N/A",
	"poster": "https://m.media-amazon.com/images/M/MV5BZDUyNmQzYTAtMzAwMS00MTU5LThjY2EtNGYzZmMzYjU3YTNjXkEyXkFqcGdeQXVyNzc5MjA3OA@@._V1_SX300.jpg",
	"ratings": [
		{
			"Source": "Internet Movie Database",
			"Value": "6.7/10"
		},
		{
			"Source": "Rotten Tomatoes",
			"Value": "89%"
		}
	],
	"metascore": "N/A",
	"rating": 6.7,
	"votes": "3,394",
	"imdbid": "tt0062301",
	"type": "movie",
	"dvd": "N/A",
	"boxoffice": "N/A",
	"production": "N/A",
	"website": "N/A",
	"response": "True",
	"name": "The St. Valentine's Day Massacre",
	"series": false,
	"imdburl": "https://www.imdb.com/title/tt0062301"
}