{
	"title": "The Ninth Day",
	"_year_data": "2004",
	"year": 2004,
	"rated": "Not Rated",
	"released": "2004-11-10T11:00:00.000Z",
	"runtime": "98 min",
	"genres": "Drama, Thriller, War",
	"director": "Volker Schlöndorff",
	"writer": "Jean Bernard (memoir \"Pfarrerblock 25487\"), Eberhard Görner (screenplay), Andreas Pflüger (screenplay)",
	"actors": "Ulrich Matthes, August Diehl, Hilmar Thate, Bibiana Beglau",
	"plot": "In World War II, after a period living hell on earth in the concentration camp of Dachau with other catholic priests, Father Abbé Henri Kremer gets a nine days leave to return to his home town for his mother's funeral. Along this period, the SS Gestapo lieutenant Gebhardt tries to persuade Henri, who was born in silver-spoon and member of an influent Luxembourgian family, to convince the local bishop to give-up resisting to the Germans and write a letter to the Vatican in the name of the Catholic Church of Luxemburg convincing the Pope to support Hitler and the Nazi regime. The ambivalent Henri questions himself and the bishop what he shall do.",
	"languages": "German, French",
	"country": "Germany, Luxembourg, Czech Republic",
	"awards": "6 wins & 13 nominations.",
	"poster": "https://m.media-amazon.com/images/M/MV5BNWYwZGIwNDMtODg0Mi00MzRlLTg3NjAtMDllNTNkMWVmODgxXkEyXkFqcGdeQXVyMzA3Njg4MzY@._V1_SX300.jpg",
	"ratings": [
		{
			"Source": "Internet Movie Database",
			"Value": "7.1/10"
		},
		{
			"Source": "Rotten Tomatoes",
			"Value": "77%"
		},
		{
			"Source": "Metacritic",
			"Value": "67/100"
		}
	],
	"metascore": "67",
	"rating": 7.1,
	"votes": "1,683",
	"imdbid": "tt0411702",
	"type": "movie",
	"dvd": "06 Dec 2005",
	"boxoffice": "N/A",
	"production": "Kino International",
	"website": "N/A",
	"response": "True",
	"name": "The Ninth Day",
	"series": false,
	"imdburl": "https://www.imdb.com/title/tt0411702"
}