{"hash":"0bc955b9a2d9abc3c624c4835ad46459cf6742a9","data":{"year":{"title":2010,"events":[{"id":"1-9-tt5121000","title":"Ramchandra Siras is seen having sex in his house with another man","dayofyear":{"path":"/1/9/","month":{"id":"1","title":"January","path":"/month/1/"},"day":{"id":"9","ordinal":"th"}},"movie":{"id":"tt5121000","path":"/tt5121000/","title":"Aligarh","year":2015}},{"id":"1-10-tt5848416","title":"Amberley Snyder is paralysed in a car crash","dayofyear":{"path":"/1/10/","month":{"id":"1","title":"January","path":"/month/1/"},"day":{"id":"10","ordinal":"th"}},"movie":{"id":"tt5848416","path":"/tt5848416/","title":"Walk. Ride. Rodeo.","year":2019}},{"id":"2-3-tt1837703","title":"Chelsea Manning sends thousands of classified documents to Wikileaks","dayofyear":{"path":"/2/3/","month":{"id":"2","title":"February","path":"/month/2/"},"day":{"id":"3","ordinal":"rd"}},"movie":{"id":"tt1837703","path":"/tt1837703/","title":"The Fifth Estate","year":2013}},{"id":"2-9-tt5121000","title":"Ramchandra Siras is suspended from his professorship at AMU","dayofyear":{"path":"/2/9/","month":{"id":"2","title":"February","path":"/month/2/"},"day":{"id":"9","ordinal":"th"}},"movie":{"id":"tt5121000","path":"/tt5121000/","title":"Aligarh","year":2015}},{"id":"3-21-tt2246565","title":"James Randi comes out as gay","dayofyear":{"path":"/3/21/","month":{"id":"3","title":"March","path":"/month/3/"},"day":{"id":"21","ordinal":"st"}},"movie":{"id":"tt2246565","path":"/tt2246565/","title":"An Honest Liar","year":2014}},{"id":"4-1-tt5121000","title":"Ramchandra Siras wins a court case arguing against his suspension","dayofyear":{"path":"/4/1/","month":{"id":"4","title":"April","path":"/month/4/"},"day":{"id":"1","ordinal":"st"}},"movie":{"id":"tt5121000","path":"/tt5121000/","title":"Aligarh","year":2015}},{"id":"4-7-tt5121000","title":"Ramchandra Siras dies","dayofyear":{"path":"/4/7/","month":{"id":"4","title":"April","path":"/month/4/"},"day":{"id":"7","ordinal":"th"}},"movie":{"id":"tt5121000","path":"/tt5121000/","title":"Aligarh","year":2015}},{"id":"4-18-tt4581310","title":"Edwin Valero is arrested for the killing of his wife","dayofyear":{"path":"/4/18/","month":{"id":"4","title":"April","path":"/month/4/"},"day":{"id":"18","ordinal":"th"}},"movie":{"id":"tt4581310","path":"/tt4581310/","title":"El Inca","year":2016}},{"id":"4-19-tt1734110","title":"the Supreme Court of India confirms Manu Sharma's life sentence for killing Jessica Lal","dayofyear":{"path":"/4/19/","month":{"id":"4","title":"April","path":"/month/4/"},"day":{"id":"19","ordinal":"th"}},"movie":{"id":"tt1734110","path":"/tt1734110/","title":"No One Killed Jessica","year":2011}},{"id":"4-20-tt1860357","title":"the Deepwater Horizon drilling rig explodes","dayofyear":{"path":"/4/20/","month":{"id":"4","title":"April","path":"/month/4/"},"day":{"id":"20","ordinal":"th"}},"movie":{"id":"tt1860357","path":"/tt1860357/","title":"Deepwater Horizon","year":2016}},{"id":"4-26-tt1648186","title":"The Fisherman's Friends release their first album under Universal Records","dayofyear":{"path":"/4/26/","month":{"id":"4","title":"April","path":"/month/4/"},"day":{"id":"26","ordinal":"th"}},"movie":{"id":"tt1648186","path":"/tt1648186/","title":"Fisherman's Friends","year":2019}},{"id":"5-18-tt4581310","title":"Edwin Valero is found hanged in his cell","dayofyear":{"path":"/5/18/","month":{"id":"5","title":"May","path":"/month/5/"},"day":{"id":"18","ordinal":"th"}},"movie":{"id":"tt4581310","path":"/tt4581310/","title":"El Inca","year":2016}},{"id":"5-29-tt1698010","title":"Start of the 2010 Isle of Man TT Races","dayofyear":{"path":"/5/29/","month":{"id":"5","title":"May","path":"/month/5/"},"day":{"id":"29","ordinal":"th"}},"movie":{"id":"tt1698010","path":"/tt1698010/","title":"TT3D: Closer to the Edge","year":2011}},{"id":"6-8-tt1194417","title":"Jack Abramoff is released from prison into a half way house","dayofyear":{"path":"/6/8/","month":{"id":"6","title":"June","path":"/month/6/"},"day":{"id":"8","ordinal":"th"}},"movie":{"id":"tt1194417","path":"/tt1194417/","title":"Casino Jack","year":2010}},{"id":"6-11-tt1698010","title":"Ian Hutchinson wins his fifth of five Isle of Man TT races","dayofyear":{"path":"/6/11/","month":{"id":"6","title":"June","path":"/month/6/"},"day":{"id":"11","ordinal":"th"}},"movie":{"id":"tt1698010","path":"/tt1698010/","title":"TT3D: Closer to the Edge","year":2011}},{"id":"6-22-tt4758646","title":"the Rolling Stone article \"The Runaway General\" is published","dayofyear":{"path":"/6/22/","month":{"id":"6","title":"June","path":"/month/6/"},"day":{"id":"22","ordinal":"nd"}},"movie":{"id":"tt4758646","path":"/tt4758646/","title":"War Machine","year":2017}},{"id":"7-24-tt1687247","title":"the footage for the documentary is filmed","dayofyear":{"path":"/7/24/","month":{"id":"7","title":"July","path":"/month/7/"},"day":{"id":"24","ordinal":"th"}},"movie":{"id":"tt1687247","path":"/tt1687247/","title":"Life in a Day","year":2011}},{"id":"7-25-tt1837703","title":"The Afghan War Logs are released on Wikileaks","dayofyear":{"path":"/7/25/","month":{"id":"7","title":"July","path":"/month/7/"},"day":{"id":"25","ordinal":"th"}},"movie":{"id":"tt1837703","path":"/tt1837703/","title":"The Fifth Estate","year":2013}},{"id":"8-5-tt2006295","title":"the San José mine collapses","dayofyear":{"path":"/8/5/","month":{"id":"8","title":"August","path":"/month/8/"},"day":{"id":"5","ordinal":"th"}},"movie":{"id":"tt2006295","path":"/tt2006295/","title":"The 33","year":2015}},{"id":"8-9-tt1136608","title":"eviction notices are served to the residents of District 9","dayofyear":{"path":"/8/9/","month":{"id":"8","title":"August","path":"/month/8/"},"day":{"id":"9","ordinal":"th"}},"movie":{"id":"tt1136608","path":"/tt1136608/","title":"District 9","year":2009}},{"id":"8-11-tt1136608","title":"Wikus escapes from MNU Headquarters","dayofyear":{"path":"/8/11/","month":{"id":"8","title":"August","path":"/month/8/"},"day":{"id":"11","ordinal":"th"}},"movie":{"id":"tt1136608","path":"/tt1136608/","title":"District 9","year":2009}},{"id":"8-13-tt1136608","title":"Wikus breaks back into MNU Headquarters","dayofyear":{"path":"/8/13/","month":{"id":"8","title":"August","path":"/month/8/"},"day":{"id":"13","ordinal":"th"}},"movie":{"id":"tt1136608","path":"/tt1136608/","title":"District 9","year":2009}},{"id":"10-7-tt5074352","title":"Geeta Phogat wins gold at the Commonwealth Games","dayofyear":{"path":"/10/7/","month":{"id":"10","title":"October","path":"/month/10/"},"day":{"id":"7","ordinal":"th"}},"movie":{"id":"tt5074352","path":"/tt5074352/","title":"Dangal","year":2016}},{"id":"10-13-tt2006295","title":"the miners are rescued","dayofyear":{"path":"/10/13/","month":{"id":"10","title":"October","path":"/month/10/"},"day":{"id":"13","ordinal":"th"}},"movie":{"id":"tt2006295","path":"/tt2006295/","title":"The 33","year":2015}},{"id":"12-3-tt1194417","title":"Jack Abramoff is released from his half way house","dayofyear":{"path":"/12/3/","month":{"id":"12","title":"December","path":"/month/12/"},"day":{"id":"3","ordinal":"rd"}},"movie":{"id":"tt1194417","path":"/tt1194417/","title":"Casino Jack","year":2010}}]}},"context":{}}