{
	"pageid": 62518854,
	"ns": 0,
	"title": "Q62721520",
	"lastrevid": 1179658834,
	"modified": "2020-05-12T11:13:05Z",
	"type": "item",
	"id": "Q62721520",
	"labels": {
		"es": {
			"language": "es",
			"value": "1917"
		},
		"de": {
			"language": "de",
			"value": "1917"
		},
		"en": {
			"language": "en",
			"value": "1917"
		},
		"ru": {
			"language": "ru",
			"value": "1917"
		},
		"uk": {
			"language": "uk",
			"value": "1917"
		},
		"fa": {
			"language": "fa",
			"value": "۱۹۱۷"
		},
		"fr": {
			"language": "fr",
			"value": "1917"
		},
		"ko": {
			"language": "ko",
			"value": "1917"
		},
		"nl": {
			"language": "nl",
			"value": "1917"
		},
		"zh": {
			"language": "zh",
			"value": "1917 (電影)"
		},
		"eu": {
			"language": "eu",
			"value": "1917 (filma)"
		},
		"id": {
			"language": "id",
			"value": "1917 (film 2019)"
		},
		"it": {
			"language": "it",
			"value": "1917"
		},
		"vi": {
			"language": "vi",
			"value": "1917 (phim 2019)"
		},
		"ja": {
			"language": "ja",
			"value": "1917 命をかけた伝令"
		},
		"ar": {
			"language": "ar",
			"value": "1917 (فيلم 2019)"
		},
		"he": {
			"language": "he",
			"value": "1917"
		},
		"tr": {
			"language": "tr",
			"value": "1917"
		},
		"lv": {
			"language": "lv",
			"value": "1917 (filma)"
		},
		"pt": {
			"language": "pt",
			"value": "1917"
		},
		"sr": {
			"language": "sr",
			"value": "1917 (филм из 2019)"
		},
		"da": {
			"language": "da",
			"value": "1917"
		},
		"pl": {
			"language": "pl",
			"value": "1917"
		},
		"be-tarask": {
			"language": "be-tarask",
			"value": "1917"
		},
		"de-ch": {
			"language": "de-ch",
			"value": "1917 (2019)"
		},
		"en-ca": {
			"language": "en-ca",
			"value": "1917 (2019 film)"
		},
		"en-gb": {
			"language": "en-gb",
			"value": "1917 (2019 film)"
		},
		"fi": {
			"language": "fi",
			"value": "Taistelulähetit – 1917"
		},
		"nb": {
			"language": "nb",
			"value": "1917"
		},
		"pt-br": {
			"language": "pt-br",
			"value": "1917 (filme de 2019)"
		},
		"sv": {
			"language": "sv",
			"value": "1917"
		},
		"el": {
			"language": "el",
			"value": "1917"
		},
		"be": {
			"language": "be",
			"value": "1917 (фільм, 2019)"
		},
		"yue": {
			"language": "yue",
			"value": "1917：逆戰救兵"
		},
		"ro": {
			"language": "ro",
			"value": "1917"
		},
		"ca": {
			"language": "ca",
			"value": "1917"
		},
		"hu": {
			"language": "hu",
			"value": "1917"
		},
		"la": {
			"language": "la",
			"value": "MCMXVII"
		},
		"mk": {
			"language": "mk",
			"value": "1917"
		},
		"cs": {
			"language": "cs",
			"value": "1917"
		},
		"sk": {
			"language": "sk",
			"value": "1917"
		},
		"uz": {
			"language": "uz",
			"value": "1917 (film, 2019)"
		},
		"hy": {
			"language": "hy",
			"value": "1917 (ֆիլմ)"
		},
		"ckb": {
			"language": "ckb",
			"value": "١٩١٧_(فیلمی_٢٠١٩)"
		},
		"hi": {
			"language": "hi",
			"value": "1917"
		},
		"bn": {
			"language": "bn",
			"value": "নাইনটিন সেভেনটিন (২০১৯-এর চলচ্চিত্র)"
		},
		"ta": {
			"language": "ta",
			"value": "1917 (ஆங்கில திரைப்படம்)"
		},
		"az": {
			"language": "az",
			"value": "1917 (film, 2019)"
		},
		"gl": {
			"language": "gl",
			"value": "1917"
		}
	},
	"descriptions": {
		"es": {
			"language": "es",
			"value": "película de guerra de Sam Mendes del 2019"
		},
		"en": {
			"language": "en",
			"value": "2019 British war film by Sam Mendes"
		},
		"fr": {
			"language": "fr",
			"value": "film sorti en 2019 et réalisé par Sam Mendes"
		},
		"nl": {
			"language": "nl",
			"value": "film van Sam Mendes"
		},
		"ru": {
			"language": "ru",
			"value": "фильм 2019 года режиссёра Сэма Мендеса"
		},
		"uk": {
			"language": "uk",
			"value": "фільм"
		},
		"fa": {
			"language": "fa",
			"value": "فیلم ۲۰۱۹"
		},
		"de": {
			"language": "de",
			"value": "Kriegsfilm von Sam Mendes (2019)"
		},
		"tr": {
			"language": "tr",
			"value": "Sam Mendes’in yönettiği 2019 yapımı film"
		},
		"da": {
			"language": "da",
			"value": "film fra 2019 af Sam Mendes"
		},
		"it": {
			"language": "it",
			"value": "film di guerra del 2019 diretto da Sam Mendes"
		},
		"pl": {
			"language": "pl",
			"value": "brytyjsko-amerykański film w reżyserii Sama Mendesa z 2019 roku"
		},
		"be-tarask": {
			"language": "be-tarask",
			"value": "брытанскі фільм"
		},
		"sv": {
			"language": "sv",
			"value": "amerikansk-brittisk film från 2019 regisserad av Sam Mendes"
		},
		"fi": {
			"language": "fi",
			"value": "Sam Mendesin ohjaama elokuva vuodelta 2019"
		},
		"el": {
			"language": "el",
			"value": "ταινία του 2019 του Σαμ Μέντες"
		},
		"ca": {
			"language": "ca",
			"value": "film del 2019 dirigit per Sam Mendes"
		},
		"ro": {
			"language": "ro",
			"value": "film din 2019 de Sam Mendes"
		},
		"nb": {
			"language": "nb",
			"value": "Drama fra Første verdenskrig"
		},
		"mk": {
			"language": "mk",
			"value": "филм на Сем Мендес од 2019 г."
		},
		"cs": {
			"language": "cs",
			"value": "film z roku 2019"
		},
		"ckb": {
			"language": "ckb",
			"value": "فیلمێکی جەنگی ٢٠١٩ی دەرھێندراو لەلایەن سام میندز"
		},
		"he": {
			"language": "he",
			"value": "סרט מלחמה"
		},
		"ja": {
			"language": "ja",
			"value": "イギリス、アメリカの映画作品"
		},
		"hi": {
			"language": "hi",
			"value": "2019 की सैम मैंडेस द्वारा निर्देशित फिल्म"
		},
		"gl": {
			"language": "gl",
			"value": "filme de 2019 dirixido por Sam Mendes"
		},
		"lv": {
			"language": "lv",
			"value": "Sema Mendesa 2019. gada filma"
		}
	},
	"aliases": {
		"nl": [
			{
				"language": "nl",
				"value": "1917 (film)"
			}
		],
		"tr": [
			{
				"language": "tr",
				"value": "1917 (film)"
			}
		],
		"da": [
			{
				"language": "da",
				"value": "1917 (film)"
			}
		],
		"fi": [
			{
				"language": "fi",
				"value": "1917"
			}
		]
	},
	"claims": {
		"P31": [
			{
				"mainsnak": {
					"snaktype": "value",
					"property": "P31",
					"datavalue": {
						"value": {
							"entity-type": "item",
							"numeric-id": 11424,
							"id": "Q11424"
						},
						"type": "wikibase-entityid"
					},
					"datatype": "wikibase-item"
				},
				"type": "statement",
				"id": "Q62721520$91fb3370-477b-6df7-db13-43728acb17ca",
				"rank": "normal"
			}
		],
		"P345": [
			{
				"mainsnak": {
					"snaktype": "value",
					"property": "P345",
					"datavalue": {
						"value": "tt8579674",
						"type": "string"
					},
					"datatype": "external-id"
				},
				"type": "statement",
				"id": "Q62721520$05ac3344-4072-f6d9-bb6b-76376c825f71",
				"rank": "normal",
				"references": [
					{
						"hash": "208ec545dc1fa2b1e0a06f2a74d3bc55d59f82d3",
						"snaks": {
							"P248": [
								{
									"snaktype": "value",
									"property": "P248",
									"datavalue": {
										"value": {
											"entity-type": "item",
											"numeric-id": 18709181,
											"id": "Q18709181"
										},
										"type": "wikibase-entityid"
									},
									"datatype": "wikibase-item"
								}
							],
							"P6127": [
								{
									"snaktype": "value",
									"property": "P6127",
									"datavalue": {
										"value": "1917",
										"type": "string"
									},
									"datatype": "external-id"
								}
							],
							"P813": [
								{
									"snaktype": "value",
									"property": "P813",
									"datavalue": {
										"value": {
											"time": "+2019-06-21T00:00:00Z",
											"timezone": 0,
											"before": 0,
											"after": 0,
											"precision": 11,
											"calendarmodel": "http://www.wikidata.org/entity/Q1985727"
										},
										"type": "time"
									},
									"datatype": "time"
								}
							]
						},
						"snaks-order": [
							"P248",
							"P6127",
							"P813"
						]
					}
				]
			}
		],
		"P577": [
			{
				"mainsnak": {
					"snaktype": "value",
					"property": "P577",
					"datavalue": {
						"value": {
							"time": "+2019-12-25T00:00:00Z",
							"timezone": 0,
							"before": 0,
							"after": 0,
							"precision": 11,
							"calendarmodel": "http://www.wikidata.org/entity/Q1985727"
						},
						"type": "time"
					},
					"datatype": "time"
				},
				"type": "statement",
				"qualifiers": {
					"P291": [
						{
							"snaktype": "value",
							"property": "P291",
							"hash": "d030038c836f9ed0d37c69cb8c389d689ebeb05a",
							"datavalue": {
								"value": {
									"entity-type": "item",
									"numeric-id": 30,
									"id": "Q30"
								},
								"type": "wikibase-entityid"
							},
							"datatype": "wikibase-item"
						}
					]
				},
				"qualifiers-order": [
					"P291"
				],
				"id": "Q62721520$da4bb7c4-423f-f5f5-c9da-4b797d401e8f",
				"rank": "normal"
			},
			{
				"mainsnak": {
					"snaktype": "value",
					"property": "P577",
					"datavalue": {
						"value": {
							"time": "+2020-01-09T00:00:00Z",
							"timezone": 0,
							"before": 0,
							"after": 0,
							"precision": 11,
							"calendarmodel": "http://www.wikidata.org/entity/Q1985727"
						},
						"type": "time"
					},
					"datatype": "time"
				},
				"type": "statement",
				"qualifiers": {
					"P291": [
						{
							"snaktype": "value",
							"property": "P291",
							"hash": "bc4a0fecf93d50193727849e64d86b19a6f81f26",
							"datavalue": {
								"value": {
									"entity-type": "item",
									"numeric-id": 55,
									"id": "Q55"
								},
								"type": "wikibase-entityid"
							},
							"datatype": "wikibase-item"
						}
					]
				},
				"qualifiers-order": [
					"P291"
				],
				"id": "Q62721520$7100077C-09B0-4640-9282-C7AF611422EE",
				"rank": "normal"
			},
			{
				"mainsnak": {
					"snaktype": "value",
					"property": "P577",
					"datavalue": {
						"value": {
							"time": "+2020-01-16T00:00:00Z",
							"timezone": 0,
							"before": 0,
							"after": 0,
							"precision": 11,
							"calendarmodel": "http://www.wikidata.org/entity/Q1985727"
						},
						"type": "time"
					},
					"datatype": "time"
				},
				"type": "statement",
				"qualifiers": {
					"P291": [
						{
							"snaktype": "value",
							"property": "P291",
							"hash": "a15ed95482d52eea03d59e098dae9e31dafef9bd",
							"datavalue": {
								"value": {
									"entity-type": "item",
									"numeric-id": 183,
									"id": "Q183"
								},
								"type": "wikibase-entityid"
							},
							"datatype": "wikibase-item"
						}
					]
				},
				"qualifiers-order": [
					"P291"
				],
				"id": "Q62721520$644464d6-434e-e6bf-dc59-e285d73f2078",
				"rank": "normal"
			},
			{
				"mainsnak": {
					"snaktype": "value",
					"property": "P577",
					"datavalue": {
						"value": {
							"time": "+2020-01-10T00:00:00Z",
							"timezone": 0,
							"before": 0,
							"after": 0,
							"precision": 11,
							"calendarmodel": "http://www.wikidata.org/entity/Q1985727"
						},
						"type": "time"
					},
					"datatype": "time"
				},
				"type": "statement",
				"qualifiers": {
					"P291": [
						{
							"snaktype": "value",
							"property": "P291",
							"hash": "46f3ab5badb2724042f6dfe60b81a99adedb8665",
							"datavalue": {
								"value": {
									"entity-type": "item",
									"numeric-id": 43,
									"id": "Q43"
								},
								"type": "wikibase-entityid"
							},
							"datatype": "wikibase-item"
						},
						{
							"snaktype": "value",
							"property": "P291",
							"hash": "0a04593d08cbf7e3266dcb4ca0b01da704269a28",
							"datavalue": {
								"value": {
									"entity-type": "item",
									"numeric-id": 145,
									"id": "Q145"
								},
								"type": "wikibase-entityid"
							},
							"datatype": "wikibase-item"
						}
					]
				},
				"qualifiers-order": [
					"P291"
				],
				"id": "Q62721520$afcec33c-4e92-4b3e-f389-285363b98ab1",
				"rank": "normal"
			},
			{
				"mainsnak": {
					"snaktype": "value",
					"property": "P577",
					"datavalue": {
						"value": {
							"time": "+2020-02-06T00:00:00Z",
							"timezone": 0,
							"before": 0,
							"after": 0,
							"precision": 11,
							"calendarmodel": "http://www.wikidata.org/entity/Q1985727"
						},
						"type": "time"
					},
					"datatype": "time"
				},
				"type": "statement",
				"qualifiers": {
					"P291": [
						{
							"snaktype": "value",
							"property": "P291",
							"hash": "8dd6692b0f05cf604df00898f8bd1efd33aa4432",
							"datavalue": {
								"value": {
									"entity-type": "item",
									"numeric-id": 28,
									"id": "Q28"
								},
								"type": "wikibase-entityid"
							},
							"datatype": "wikibase-item"
						}
					]
				},
				"qualifiers-order": [
					"P291"
				],
				"id": "Q62721520$09FAC108-3ACA-48F6-8565-6159449BB715",
				"rank": "normal",
				"references": [
					{
						"hash": "c3fd8bb917feaf9544e2df9f8fb76a310dfd3f15",
						"snaks": {
							"P854": [
								{
									"snaktype": "value",
									"property": "P854",
									"datavalue": {
										"value": "http://nmhh.hu/dokumentum/198182/terjesztett_filmalkotasok_art_filmek_nyilvantartasa.xlsx",
										"type": "string"
									},
									"datatype": "url"
								}
							]
						},
						"snaks-order": [
							"P854"
						]
					}
				]
			},
			{
				"mainsnak": {
					"snaktype": "value",
					"property": "P577",
					"datavalue": {
						"value": {
							"time": "+2020-01-10T00:00:00Z",
							"timezone": 0,
							"before": 0,
							"after": 0,
							"precision": 11,
							"calendarmodel": "http://www.wikidata.org/entity/Q1985727"
						},
						"type": "time"
					},
					"datatype": "time"
				},
				"type": "statement",
				"qualifiers": {
					"P291": [
						{
							"snaktype": "value",
							"property": "P291",
							"hash": "b8394ebff3a0bc505e21e08964c9af571cf265d9",
							"datavalue": {
								"value": {
									"entity-type": "item",
									"numeric-id": 211,
									"id": "Q211"
								},
								"type": "wikibase-entityid"
							},
							"datatype": "wikibase-item"
						}
					]
				},
				"qualifiers-order": [
					"P291"
				],
				"id": "Q62721520$8ebf7e1d-4aa1-abb8-e1d1-66ad81088b90",
				"rank": "normal"
			}
		],
		"P57": [
			{
				"mainsnak": {
					"snaktype": "value",
					"property": "P57",
					"datavalue": {
						"value": {
							"entity-type": "item",
							"numeric-id": 223233,
							"id": "Q223233"
						},
						"type": "wikibase-entityid"
					},
					"datatype": "wikibase-item"
				},
				"type": "statement",
				"id": "Q62721520$aca12974-4798-6b07-0f43-e220eed5b35d",
				"rank": "normal",
				"references": [
					{
						"hash": "697ebe753b838814bf6eb9bc6d52bbae34d1a790",
						"snaks": {
							"P248": [
								{
									"snaktype": "value",
									"property": "P248",
									"datavalue": {
										"value": {
											"entity-type": "item",
											"numeric-id": 3561957,
											"id": "Q3561957"
										},
										"type": "wikibase-entityid"
									},
									"datatype": "wikibase-item"
								}
							]
						},
						"snaks-order": [
							"P248"
						]
					},
					{
						"hash": "6cf6b5e612e76c45254864922c613af4f83e1649",
						"snaks": {
							"P854": [
								{
									"snaktype": "value",
									"property": "P854",
									"datavalue": {
										"value": "https://theworldofmovies.com/1917-movie-review/",
										"type": "string"
									},
									"datatype": "url"
								}
							]
						},
						"snaks-order": [
							"P854"
						]
					}
				]
			}
		],
		"P162": [
			{
				"mainsnak": {
					"snaktype": "value",
					"property": "P162",
					"datavalue": {
						"value": {
							"entity-type": "item",
							"numeric-id": 23418582,
							"id": "Q23418582"
						},
						"type": "wikibase-entityid"
					},
					"datatype": "wikibase-item"
				},
				"type": "statement",
				"id": "Q62721520$c7f0ed0b-440b-ba7c-39ec-171ab3101315",
				"rank": "normal"
			},
			{
				"mainsnak": {
					"snaktype": "value",
					"property": "P162",
					"datavalue": {
						"value": {
							"entity-type": "item",
							"numeric-id": 24808978,
							"id": "Q24808978"
						},
						"type": "wikibase-entityid"
					},
					"datatype": "wikibase-item"
				},
				"type": "statement",
				"id": "Q62721520$d7c63a39-42c3-3857-aef1-2e596aca1087",
				"rank": "normal"
			},
			{
				"mainsnak": {
					"snaktype": "value",
					"property": "P162",
					"datavalue": {
						"value": {
							"entity-type": "item",
							"numeric-id": 223233,
							"id": "Q223233"
						},
						"type": "wikibase-entityid"
					},
					"datatype": "wikibase-item"
				},
				"type": "statement",
				"id": "Q62721520$6cdea3c3-4649-0b19-37db-07462f7c0659",
				"rank": "normal"
			},
			{
				"mainsnak": {
					"snaktype": "value",
					"property": "P162",
					"datavalue": {
						"value": {
							"entity-type": "item",
							"numeric-id": 62721617,
							"id": "Q62721617"
						},
						"type": "wikibase-entityid"
					},
					"datatype": "wikibase-item"
				},
				"type": "statement",
				"id": "Q62721520$6fa48f76-4bf9-60a2-b3db-294171417315",
				"rank": "normal"
			}
		],
		"P58": [
			{
				"mainsnak": {
					"snaktype": "value",
					"property": "P58",
					"datavalue": {
						"value": {
							"entity-type": "item",
							"numeric-id": 223233,
							"id": "Q223233"
						},
						"type": "wikibase-entityid"
					},
					"datatype": "wikibase-item"
				},
				"type": "statement",
				"id": "Q62721520$aa5ab527-4a6d-633f-5787-2d55f3518f5c",
				"rank": "normal",
				"references": [
					{
						"hash": "697ebe753b838814bf6eb9bc6d52bbae34d1a790",
						"snaks": {
							"P248": [
								{
									"snaktype": "value",
									"property": "P248",
									"datavalue": {
										"value": {
											"entity-type": "item",
											"numeric-id": 3561957,
											"id": "Q3561957"
										},
										"type": "wikibase-entityid"
									},
									"datatype": "wikibase-item"
								}
							]
						},
						"snaks-order": [
							"P248"
						]
					}
				]
			},
			{
				"mainsnak": {
					"snaktype": "value",
					"property": "P58",
					"datavalue": {
						"value": {
							"entity-type": "item",
							"numeric-id": 62019312,
							"id": "Q62019312"
						},
						"type": "wikibase-entityid"
					},
					"datatype": "wikibase-item"
				},
				"type": "statement",
				"id": "Q62721520$9cd6cff8-4d1b-8c46-714c-a2a8a4af5ba3",
				"rank": "normal"
			}
		],
		"P161": [
			{
				"mainsnak": {
					"snaktype": "value",
					"property": "P161",
					"datavalue": {
						"value": {
							"entity-type": "item",
							"numeric-id": 970066,
							"id": "Q970066"
						},
						"type": "wikibase-entityid"
					},
					"datatype": "wikibase-item"
				},
				"type": "statement",
				"id": "Q62721520$96917c4e-4c1a-6661-72b1-9c3e0bf547c3",
				"rank": "normal",
				"references": [
					{
						"hash": "697ebe753b838814bf6eb9bc6d52bbae34d1a790",
						"snaks": {
							"P248": [
								{
									"snaktype": "value",
									"property": "P248",
									"datavalue": {
										"value": {
											"entity-type": "item",
											"numeric-id": 3561957,
											"id": "Q3561957"
										},
										"type": "wikibase-entityid"
									},
									"datatype": "wikibase-item"
								}
							]
						},
						"snaks-order": [
							"P248"
						]
					}
				]
			},
			{
				"mainsnak": {
					"snaktype": "value",
					"property": "P161",
					"datavalue": {
						"value": {
							"entity-type": "item",
							"numeric-id": 16713577,
							"id": "Q16713577"
						},
						"type": "wikibase-entityid"
					},
					"datatype": "wikibase-item"
				},
				"type": "statement",
				"id": "Q62721520$e27a62fc-4158-9414-7778-a498365f3c51",
				"rank": "normal",
				"references": [
					{
						"hash": "697ebe753b838814bf6eb9bc6d52bbae34d1a790",
						"snaks": {
							"P248": [
								{
									"snaktype": "value",
									"property": "P248",
									"datavalue": {
										"value": {
											"entity-type": "item",
											"numeric-id": 3561957,
											"id": "Q3561957"
										},
										"type": "wikibase-entityid"
									},
									"datatype": "wikibase-item"
								}
							]
						},
						"snaks-order": [
							"P248"
						]
					}
				]
			},
			{
				"mainsnak": {
					"snaktype": "value",
					"property": "P161",
					"datavalue": {
						"value": {
							"entity-type": "item",
							"numeric-id": 244674,
							"id": "Q244674"
						},
						"type": "wikibase-entityid"
					},
					"datatype": "wikibase-item"
				},
				"type": "statement",
				"id": "Q62721520$df656794-4aee-f328-b2b0-c1502816b14c",
				"rank": "normal",
				"references": [
					{
						"hash": "697ebe753b838814bf6eb9bc6d52bbae34d1a790",
						"snaks": {
							"P248": [
								{
									"snaktype": "value",
									"property": "P248",
									"datavalue": {
										"value": {
											"entity-type": "item",
											"numeric-id": 3561957,
											"id": "Q3561957"
										},
										"type": "wikibase-entityid"
									},
									"datatype": "wikibase-item"
								}
							]
						},
						"snaks-order": [
							"P248"
						]
					}
				]
			},
			{
				"mainsnak": {
					"snaktype": "value",
					"property": "P161",
					"datavalue": {
						"value": {
							"entity-type": "item",
							"numeric-id": 162492,
							"id": "Q162492"
						},
						"type": "wikibase-entityid"
					},
					"datatype": "wikibase-item"
				},
				"type": "statement",
				"id": "Q62721520$f0fc6d89-477a-90a3-d190-f5e5cb8b32d0",
				"rank": "normal",
				"references": [
					{
						"hash": "697ebe753b838814bf6eb9bc6d52bbae34d1a790",
						"snaks": {
							"P248": [
								{
									"snaktype": "value",
									"property": "P248",
									"datavalue": {
										"value": {
											"entity-type": "item",
											"numeric-id": 3561957,
											"id": "Q3561957"
										},
										"type": "wikibase-entityid"
									},
									"datatype": "wikibase-item"
								}
							]
						},
						"snaks-order": [
							"P248"
						]
					}
				]
			},
			{
				"mainsnak": {
					"snaktype": "value",
					"property": "P161",
					"datavalue": {
						"value": {
							"entity-type": "item",
							"numeric-id": 312712,
							"id": "Q312712"
						},
						"type": "wikibase-entityid"
					},
					"datatype": "wikibase-item"
				},
				"type": "statement",
				"id": "Q62721520$fa0f9350-43ec-ad22-ba64-319ab81b7d4e",
				"rank": "normal",
				"references": [
					{
						"hash": "697ebe753b838814bf6eb9bc6d52bbae34d1a790",
						"snaks": {
							"P248": [
								{
									"snaktype": "value",
									"property": "P248",
									"datavalue": {
										"value": {
											"entity-type": "item",
											"numeric-id": 3561957,
											"id": "Q3561957"
										},
										"type": "wikibase-entityid"
									},
									"datatype": "wikibase-item"
								}
							]
						},
						"snaks-order": [
							"P248"
						]
					}
				]
			},
			{
				"mainsnak": {
					"snaktype": "value",
					"property": "P161",
					"datavalue": {
						"value": {
							"entity-type": "item",
							"numeric-id": 510848,
							"id": "Q510848"
						},
						"type": "wikibase-entityid"
					},
					"datatype": "wikibase-item"
				},
				"type": "statement",
				"id": "Q62721520$69c96832-4a1a-fc37-1401-d566d2665a1d",
				"rank": "normal",
				"references": [
					{
						"hash": "697ebe753b838814bf6eb9bc6d52bbae34d1a790",
						"snaks": {
							"P248": [
								{
									"snaktype": "value",
									"property": "P248",
									"datavalue": {
										"value": {
											"entity-type": "item",
											"numeric-id": 3561957,
											"id": "Q3561957"
										},
										"type": "wikibase-entityid"
									},
									"datatype": "wikibase-item"
								}
							]
						},
						"snaks-order": [
							"P248"
						]
					}
				]
			},
			{
				"mainsnak": {
					"snaktype": "value",
					"property": "P161",
					"datavalue": {
						"value": {
							"entity-type": "item",
							"numeric-id": 507322,
							"id": "Q507322"
						},
						"type": "wikibase-entityid"
					},
					"datatype": "wikibase-item"
				},
				"type": "statement",
				"id": "Q62721520$8FA862E5-3708-40E7-A364-108149C16C62",
				"rank": "normal",
				"references": [
					{
						"hash": "697ebe753b838814bf6eb9bc6d52bbae34d1a790",
						"snaks": {
							"P248": [
								{
									"snaktype": "value",
									"property": "P248",
									"datavalue": {
										"value": {
											"entity-type": "item",
											"numeric-id": 3561957,
											"id": "Q3561957"
										},
										"type": "wikibase-entityid"
									},
									"datatype": "wikibase-item"
								}
							]
						},
						"snaks-order": [
							"P248"
						]
					}
				]
			},
			{
				"mainsnak": {
					"snaktype": "value",
					"property": "P161",
					"datavalue": {
						"value": {
							"entity-type": "item",
							"numeric-id": 1242707,
							"id": "Q1242707"
						},
						"type": "wikibase-entityid"
					},
					"datatype": "wikibase-item"
				},
				"type": "statement",
				"id": "Q62721520$83C6452D-9358-4DFC-91EB-137DA33883CD",
				"rank": "normal",
				"references": [
					{
						"hash": "697ebe753b838814bf6eb9bc6d52bbae34d1a790",
						"snaks": {
							"P248": [
								{
									"snaktype": "value",
									"property": "P248",
									"datavalue": {
										"value": {
											"entity-type": "item",
											"numeric-id": 3561957,
											"id": "Q3561957"
										},
										"type": "wikibase-entityid"
									},
									"datatype": "wikibase-item"
								}
							]
						},
						"snaks-order": [
							"P248"
						]
					}
				]
			},
			{
				"mainsnak": {
					"snaktype": "value",
					"property": "P161",
					"datavalue": {
						"value": {
							"entity-type": "item",
							"numeric-id": 579571,
							"id": "Q579571"
						},
						"type": "wikibase-entityid"
					},
					"datatype": "wikibase-item"
				},
				"type": "statement",
				"id": "Q62721520$8D34BCCE-C9AD-4993-B100-90DD8D1E9F09",
				"rank": "normal",
				"references": [
					{
						"hash": "697ebe753b838814bf6eb9bc6d52bbae34d1a790",
						"snaks": {
							"P248": [
								{
									"snaktype": "value",
									"property": "P248",
									"datavalue": {
										"value": {
											"entity-type": "item",
											"numeric-id": 3561957,
											"id": "Q3561957"
										},
										"type": "wikibase-entityid"
									},
									"datatype": "wikibase-item"
								}
							]
						},
						"snaks-order": [
							"P248"
						]
					}
				]
			},
			{
				"mainsnak": {
					"snaktype": "value",
					"property": "P161",
					"datavalue": {
						"value": {
							"entity-type": "item",
							"numeric-id": 361465,
							"id": "Q361465"
						},
						"type": "wikibase-entityid"
					},
					"datatype": "wikibase-item"
				},
				"type": "statement",
				"id": "Q62721520$88B53B9A-7A77-478C-BEC5-1B3AEBF34A72",
				"rank": "normal",
				"references": [
					{
						"hash": "697ebe753b838814bf6eb9bc6d52bbae34d1a790",
						"snaks": {
							"P248": [
								{
									"snaktype": "value",
									"property": "P248",
									"datavalue": {
										"value": {
											"entity-type": "item",
											"numeric-id": 3561957,
											"id": "Q3561957"
										},
										"type": "wikibase-entityid"
									},
									"datatype": "wikibase-item"
								}
							]
						},
						"snaks-order": [
							"P248"
						]
					}
				]
			},
			{
				"mainsnak": {
					"snaktype": "value",
					"property": "P161",
					"datavalue": {
						"value": {
							"entity-type": "item",
							"numeric-id": 547670,
							"id": "Q547670"
						},
						"type": "wikibase-entityid"
					},
					"datatype": "wikibase-item"
				},
				"type": "statement",
				"id": "Q62721520$FEF6D302-1348-4F10-8379-47D7D24D4614",
				"rank": "normal",
				"references": [
					{
						"hash": "697ebe753b838814bf6eb9bc6d52bbae34d1a790",
						"snaks": {
							"P248": [
								{
									"snaktype": "value",
									"property": "P248",
									"datavalue": {
										"value": {
											"entity-type": "item",
											"numeric-id": 3561957,
											"id": "Q3561957"
										},
										"type": "wikibase-entityid"
									},
									"datatype": "wikibase-item"
								}
							]
						},
						"snaks-order": [
							"P248"
						]
					}
				]
			},
			{
				"mainsnak": {
					"snaktype": "value",
					"property": "P161",
					"datavalue": {
						"value": {
							"entity-type": "item",
							"numeric-id": 16231541,
							"id": "Q16231541"
						},
						"type": "wikibase-entityid"
					},
					"datatype": "wikibase-item"
				},
				"type": "statement",
				"id": "Q62721520$BD35C2E5-B4FE-4527-BCE1-2C72439DB7E9",
				"rank": "normal",
				"references": [
					{
						"hash": "697ebe753b838814bf6eb9bc6d52bbae34d1a790",
						"snaks": {
							"P248": [
								{
									"snaktype": "value",
									"property": "P248",
									"datavalue": {
										"value": {
											"entity-type": "item",
											"numeric-id": 3561957,
											"id": "Q3561957"
										},
										"type": "wikibase-entityid"
									},
									"datatype": "wikibase-item"
								}
							]
						},
						"snaks-order": [
							"P248"
						]
					}
				]
			},
			{
				"mainsnak": {
					"snaktype": "value",
					"property": "P161",
					"datavalue": {
						"value": {
							"entity-type": "item",
							"numeric-id": 6831635,
							"id": "Q6831635"
						},
						"type": "wikibase-entityid"
					},
					"datatype": "wikibase-item"
				},
				"type": "statement",
				"id": "Q62721520$5157DD56-1C8D-4B19-930C-156D38656925",
				"rank": "normal",
				"references": [
					{
						"hash": "697ebe753b838814bf6eb9bc6d52bbae34d1a790",
						"snaks": {
							"P248": [
								{
									"snaktype": "value",
									"property": "P248",
									"datavalue": {
										"value": {
											"entity-type": "item",
											"numeric-id": 3561957,
											"id": "Q3561957"
										},
										"type": "wikibase-entityid"
									},
									"datatype": "wikibase-item"
								}
							]
						},
						"snaks-order": [
							"P248"
						]
					}
				]
			},
			{
				"mainsnak": {
					"snaktype": "value",
					"property": "P161",
					"datavalue": {
						"value": {
							"entity-type": "item",
							"numeric-id": 3934844,
							"id": "Q3934844"
						},
						"type": "wikibase-entityid"
					},
					"datatype": "wikibase-item"
				},
				"type": "statement",
				"id": "Q62721520$901253BA-7C76-45B3-ADB6-1B7DBAA86872",
				"rank": "normal",
				"references": [
					{
						"hash": "697ebe753b838814bf6eb9bc6d52bbae34d1a790",
						"snaks": {
							"P248": [
								{
									"snaktype": "value",
									"property": "P248",
									"datavalue": {
										"value": {
											"entity-type": "item",
											"numeric-id": 3561957,
											"id": "Q3561957"
										},
										"type": "wikibase-entityid"
									},
									"datatype": "wikibase-item"
								}
							]
						},
						"snaks-order": [
							"P248"
						]
					}
				]
			}
		],
		"P495": [
			{
				"mainsnak": {
					"snaktype": "value",
					"property": "P495",
					"datavalue": {
						"value": {
							"entity-type": "item",
							"numeric-id": 145,
							"id": "Q145"
						},
						"type": "wikibase-entityid"
					},
					"datatype": "wikibase-item"
				},
				"type": "statement",
				"id": "Q62721520$362f706f-4dc5-238d-faaa-e99d54c72f5c",
				"rank": "normal"
			},
			{
				"mainsnak": {
					"snaktype": "value",
					"property": "P495",
					"datavalue": {
						"value": {
							"entity-type": "item",
							"numeric-id": 30,
							"id": "Q30"
						},
						"type": "wikibase-entityid"
					},
					"datatype": "wikibase-item"
				},
				"type": "statement",
				"id": "Q62721520$fd5cb906-4156-9e3b-2b37-7337db0be510",
				"rank": "normal"
			}
		],
		"P86": [
			{
				"mainsnak": {
					"snaktype": "value",
					"property": "P86",
					"datavalue": {
						"value": {
							"entity-type": "item",
							"numeric-id": 319996,
							"id": "Q319996"
						},
						"type": "wikibase-entityid"
					},
					"datatype": "wikibase-item"
				},
				"type": "statement",
				"id": "Q62721520$d0252731-4133-0338-facb-0e2343eae0b9",
				"rank": "normal"
			}
		],
		"P344": [
			{
				"mainsnak": {
					"snaktype": "value",
					"property": "P344",
					"datavalue": {
						"value": {
							"entity-type": "item",
							"numeric-id": 460277,
							"id": "Q460277"
						},
						"type": "wikibase-entityid"
					},
					"datatype": "wikibase-item"
				},
				"type": "statement",
				"id": "Q62721520$cf889316-4891-0a2b-3032-af16ebfd0c1b",
				"rank": "normal"
			}
		],
		"P364": [
			{
				"mainsnak": {
					"snaktype": "value",
					"property": "P364",
					"datavalue": {
						"value": {
							"entity-type": "item",
							"numeric-id": 1860,
							"id": "Q1860"
						},
						"type": "wikibase-entityid"
					},
					"datatype": "wikibase-item"
				},
				"type": "statement",
				"id": "Q62721520$d2fe6c0a-4bb0-d19c-b752-fed33becbf7f",
				"rank": "normal"
			}
		],
		"P1040": [
			{
				"mainsnak": {
					"snaktype": "value",
					"property": "P1040",
					"datavalue": {
						"value": {
							"entity-type": "item",
							"numeric-id": 1811998,
							"id": "Q1811998"
						},
						"type": "wikibase-entityid"
					},
					"datatype": "wikibase-item"
				},
				"type": "statement",
				"id": "Q62721520$e4221da5-4501-a4f8-f16e-7e63a52b1a61",
				"rank": "normal"
			}
		],
		"P1476": [
			{
				"mainsnak": {
					"snaktype": "value",
					"property": "P1476",
					"datavalue": {
						"value": {
							"text": "1917",
							"language": "en"
						},
						"type": "monolingualtext"
					},
					"datatype": "monolingualtext"
				},
				"type": "statement",
				"id": "Q62721520$7544fedd-41a4-88d8-5f9f-2a06c454965f",
				"rank": "normal"
			}
		],
		"P136": [
			{
				"mainsnak": {
					"snaktype": "value",
					"property": "P136",
					"datavalue": {
						"value": {
							"entity-type": "item",
							"numeric-id": 369747,
							"id": "Q369747"
						},
						"type": "wikibase-entityid"
					},
					"datatype": "wikibase-item"
				},
				"type": "statement",
				"id": "Q62721520$b4c7dad7-471d-d492-a6e4-fd0a1479e21a",
				"rank": "normal"
			},
			{
				"mainsnak": {
					"snaktype": "value",
					"property": "P136",
					"datavalue": {
						"value": {
							"entity-type": "item",
							"numeric-id": 130232,
							"id": "Q130232"
						},
						"type": "wikibase-entityid"
					},
					"datatype": "wikibase-item"
				},
				"type": "statement",
				"id": "Q62721520$784F374E-7992-4DA7-879B-6A4532289AB4",
				"rank": "normal",
				"references": [
					{
						"hash": "a9ea16a35f21fe85fab3b892332fbea56e01b363",
						"snaks": {
							"P3452": [
								{
									"snaktype": "value",
									"property": "P3452",
									"datavalue": {
										"value": {
											"entity-type": "item",
											"numeric-id": 6836797,
											"id": "Q6836797"
										},
										"type": "wikibase-entityid"
									},
									"datatype": "wikibase-item"
								}
							],
							"P813": [
								{
									"snaktype": "value",
									"property": "P813",
									"datavalue": {
										"value": {
											"time": "+2019-05-27T00:00:00Z",
											"timezone": 0,
											"before": 0,
											"after": 0,
											"precision": 11,
											"calendarmodel": "http://www.wikidata.org/entity/Q1985727"
										},
										"type": "time"
									},
									"datatype": "time"
								}
							],
							"P143": [
								{
									"snaktype": "value",
									"property": "P143",
									"datavalue": {
										"value": {
											"entity-type": "item",
											"numeric-id": 328,
											"id": "Q328"
										},
										"type": "wikibase-entityid"
									},
									"datatype": "wikibase-item"
								},
								{
									"snaktype": "value",
									"property": "P143",
									"datavalue": {
										"value": {
											"entity-type": "item",
											"numeric-id": 8449,
											"id": "Q8449"
										},
										"type": "wikibase-entityid"
									},
									"datatype": "wikibase-item"
								}
							]
						},
						"snaks-order": [
							"P3452",
							"P813",
							"P143"
						]
					}
				]
			}
		],
		"P272": [
			{
				"mainsnak": {
					"snaktype": "value",
					"property": "P272",
					"datavalue": {
						"value": {
							"entity-type": "item",
							"numeric-id": 22079339,
							"id": "Q22079339"
						},
						"type": "wikibase-entityid"
					},
					"datatype": "wikibase-item"
				},
				"type": "statement",
				"id": "Q62721520$72a351bc-46ff-7c55-7ea5-73853a8c5eaa",
				"rank": "normal"
			},
			{
				"mainsnak": {
					"snaktype": "value",
					"property": "P272",
					"datavalue": {
						"value": {
							"entity-type": "item",
							"numeric-id": 6984198,
							"id": "Q6984198"
						},
						"type": "wikibase-entityid"
					},
					"datatype": "wikibase-item"
				},
				"type": "statement",
				"id": "Q62721520$5623ae78-418a-3d56-5b24-4eff8a8ae44f",
				"rank": "normal"
			}
		],
		"P750": [
			{
				"mainsnak": {
					"snaktype": "value",
					"property": "P750",
					"datavalue": {
						"value": {
							"entity-type": "item",
							"numeric-id": 168383,
							"id": "Q168383"
						},
						"type": "wikibase-entityid"
					},
					"datatype": "wikibase-item"
				},
				"type": "statement",
				"id": "Q62721520$f2725749-4b3e-54ba-9a51-0d1d148dabfc",
				"rank": "normal"
			}
		],
		"P480": [
			{
				"mainsnak": {
					"snaktype": "value",
					"property": "P480",
					"datavalue": {
						"value": "145446",
						"type": "string"
					},
					"datatype": "external-id"
				},
				"type": "statement",
				"id": "Q62721520$6f6ce680-4503-ce79-6af4-b573a203a8ab",
				"rank": "normal"
			}
		],
		"P4947": [
			{
				"mainsnak": {
					"snaktype": "value",
					"property": "P4947",
					"datavalue": {
						"value": "530915",
						"type": "string"
					},
					"datatype": "external-id"
				},
				"type": "statement",
				"id": "Q62721520$E2AD3569-CA59-45A5-9EFF-E0A4B168F82A",
				"rank": "normal",
				"references": [
					{
						"hash": "208ec545dc1fa2b1e0a06f2a74d3bc55d59f82d3",
						"snaks": {
							"P248": [
								{
									"snaktype": "value",
									"property": "P248",
									"datavalue": {
										"value": {
											"entity-type": "item",
											"numeric-id": 18709181,
											"id": "Q18709181"
										},
										"type": "wikibase-entityid"
									},
									"datatype": "wikibase-item"
								}
							],
							"P6127": [
								{
									"snaktype": "value",
									"property": "P6127",
									"datavalue": {
										"value": "1917",
										"type": "string"
									},
									"datatype": "external-id"
								}
							],
							"P813": [
								{
									"snaktype": "value",
									"property": "P813",
									"datavalue": {
										"value": {
											"time": "+2019-06-21T00:00:00Z",
											"timezone": 0,
											"before": 0,
											"after": 0,
											"precision": 11,
											"calendarmodel": "http://www.wikidata.org/entity/Q1985727"
										},
										"type": "time"
									},
									"datatype": "time"
								}
							]
						},
						"snaks-order": [
							"P248",
							"P6127",
							"P813"
						]
					}
				]
			}
		],
		"P462": [
			{
				"mainsnak": {
					"snaktype": "value",
					"property": "P462",
					"datavalue": {
						"value": {
							"entity-type": "item",
							"numeric-id": 22006653,
							"id": "Q22006653"
						},
						"type": "wikibase-entityid"
					},
					"datatype": "wikibase-item"
				},
				"type": "statement",
				"id": "Q62721520$ef1bc5fc-45f8-20d6-5c34-d1c83d35884d",
				"rank": "normal"
			}
		],
		"P6127": [
			{
				"mainsnak": {
					"snaktype": "value",
					"property": "P6127",
					"datavalue": {
						"value": "1917",
						"type": "string"
					},
					"datatype": "external-id"
				},
				"type": "statement",
				"id": "Q62721520$4E6DE5EC-BCB5-40CC-B41D-66233AE18EB6",
				"rank": "normal",
				"references": [
					{
						"hash": "208ec545dc1fa2b1e0a06f2a74d3bc55d59f82d3",
						"snaks": {
							"P248": [
								{
									"snaktype": "value",
									"property": "P248",
									"datavalue": {
										"value": {
											"entity-type": "item",
											"numeric-id": 18709181,
											"id": "Q18709181"
										},
										"type": "wikibase-entityid"
									},
									"datatype": "wikibase-item"
								}
							],
							"P6127": [
								{
									"snaktype": "value",
									"property": "P6127",
									"datavalue": {
										"value": "1917",
										"type": "string"
									},
									"datatype": "external-id"
								}
							],
							"P813": [
								{
									"snaktype": "value",
									"property": "P813",
									"datavalue": {
										"value": {
											"time": "+2019-06-21T00:00:00Z",
											"timezone": 0,
											"before": 0,
											"after": 0,
											"precision": 11,
											"calendarmodel": "http://www.wikidata.org/entity/Q1985727"
										},
										"type": "time"
									},
									"datatype": "time"
								}
							]
						},
						"snaks-order": [
							"P248",
							"P6127",
							"P813"
						]
					}
				]
			}
		],
		"P1265": [
			{
				"mainsnak": {
					"snaktype": "value",
					"property": "P1265",
					"datavalue": {
						"value": "265567",
						"type": "string"
					},
					"datatype": "external-id"
				},
				"type": "statement",
				"id": "Q62721520$64A3E506-6245-4ADC-B422-0B81A664EE6B",
				"rank": "normal",
				"references": [
					{
						"hash": "2a0cfb37122e8d6e60acdf45e69f2eebe266b6b5",
						"snaks": {
							"P143": [
								{
									"snaktype": "value",
									"property": "P143",
									"datavalue": {
										"value": {
											"entity-type": "item",
											"numeric-id": 8447,
											"id": "Q8447"
										},
										"type": "wikibase-entityid"
									},
									"datatype": "wikibase-item"
								}
							],
							"P4656": [
								{
									"snaktype": "value",
									"property": "P4656",
									"datavalue": {
										"value": "https://fr.wikipedia.org/w/index.php?title=1917_(film)&oldid=159234489",
										"type": "string"
									},
									"datatype": "url"
								}
							]
						},
						"snaks-order": [
							"P143",
							"P4656"
						]
					}
				]
			}
		],
		"P856": [
			{
				"mainsnak": {
					"snaktype": "value",
					"property": "P856",
					"datavalue": {
						"value": "https://www.1917.movie/",
						"type": "string"
					},
					"datatype": "url"
				},
				"type": "statement",
				"qualifiers": {
					"P407": [
						{
							"snaktype": "value",
							"property": "P407",
							"hash": "daf1c4fcb58181b02dff9cc89deb084004ddae4b",
							"datavalue": {
								"value": {
									"entity-type": "item",
									"numeric-id": 1860,
									"id": "Q1860"
								},
								"type": "wikibase-entityid"
							},
							"datatype": "wikibase-item"
						}
					]
				},
				"qualifiers-order": [
					"P407"
				],
				"id": "Q62721520$36207905-4df9-2aa8-d72c-ee29a3276a9d",
				"rank": "normal"
			}
		],
		"P1657": [
			{
				"mainsnak": {
					"snaktype": "value",
					"property": "P1657",
					"datavalue": {
						"value": {
							"entity-type": "item",
							"numeric-id": 18665344,
							"id": "Q18665344"
						},
						"type": "wikibase-entityid"
					},
					"datatype": "wikibase-item"
				},
				"type": "statement",
				"qualifiers": {
					"P2676": [
						{
							"snaktype": "value",
							"property": "P2676",
							"hash": "e9af9a7ffdfb1f3d4bbd41e5dca4b1bc3044380e",
							"datavalue": {
								"value": "52437",
								"type": "string"
							},
							"datatype": "string"
						}
					]
				},
				"qualifiers-order": [
					"P2676"
				],
				"id": "Q62721520$dce5a443-4f96-9724-bb4f-2710c17b1a00",
				"rank": "normal"
			}
		],
		"P840": [
			{
				"mainsnak": {
					"snaktype": "value",
					"property": "P840",
					"datavalue": {
						"value": {
							"entity-type": "item",
							"numeric-id": 142,
							"id": "Q142"
						},
						"type": "wikibase-entityid"
					},
					"datatype": "wikibase-item"
				},
				"type": "statement",
				"id": "Q62721520$02fac75a-ec84-4802-8589-4570cae2a00f",
				"rank": "normal",
				"references": [
					{
						"hash": "a29a646602abf65105ed0f39a44231c962ece9ee",
						"snaks": {
							"P143": [
								{
									"snaktype": "value",
									"property": "P143",
									"datavalue": {
										"value": {
											"entity-type": "item",
											"numeric-id": 177837,
											"id": "Q177837"
										},
										"type": "wikibase-entityid"
									},
									"datatype": "wikibase-item"
								}
							]
						},
						"snaks-order": [
							"P143"
						]
					}
				]
			}
		],
		"P2002": [
			{
				"mainsnak": {
					"snaktype": "value",
					"property": "P2002",
					"datavalue": {
						"value": "1917",
						"type": "string"
					},
					"datatype": "external-id"
				},
				"type": "statement",
				"qualifiers": {
					"P6552": [
						{
							"snaktype": "value",
							"property": "P6552",
							"hash": "052e59927394a4de7b55943f1e7bf92b0c30a52c",
							"datavalue": {
								"value": "1126258646000652288",
								"type": "string"
							},
							"datatype": "external-id"
						}
					],
					"P1552": [
						{
							"snaktype": "value",
							"property": "P1552",
							"hash": "62f0039d240f7eeba6c6908a0d8807a6188324a1",
							"datavalue": {
								"value": {
									"entity-type": "item",
									"numeric-id": 28378282,
									"id": "Q28378282"
								},
								"type": "wikibase-entityid"
							},
							"datatype": "wikibase-item"
						}
					],
					"P585": [
						{
							"snaktype": "value",
							"property": "P585",
							"hash": "08d43e6d134946ccc1643f9b8079aa0253324e8d",
							"datavalue": {
								"value": {
									"time": "+2020-02-27T00:00:00Z",
									"timezone": 0,
									"before": 0,
									"after": 0,
									"precision": 11,
									"calendarmodel": "http://www.wikidata.org/entity/Q1985727"
								},
								"type": "time"
							},
							"datatype": "time"
						}
					]
				},
				"qualifiers-order": [
					"P6552",
					"P1552",
					"P585"
				],
				"id": "Q62721520$c1dc0c3b-41fd-5c60-bbda-423267f94c07",
				"rank": "normal"
			}
		],
		"P3077": [
			{
				"mainsnak": {
					"snaktype": "value",
					"property": "P3077",
					"datavalue": {
						"value": "362504",
						"type": "string"
					},
					"datatype": "external-id"
				},
				"type": "statement",
				"id": "Q62721520$39b5c367-4632-75e4-b6b7-c8e21a59bc26",
				"rank": "normal",
				"references": [
					{
						"hash": "65b3dd3cf5f4970a4bd5090a710c260ad729e777",
						"snaks": {
							"P248": [
								{
									"snaktype": "value",
									"property": "P248",
									"datavalue": {
										"value": {
											"entity-type": "item",
											"numeric-id": 1092476,
											"id": "Q1092476"
										},
										"type": "wikibase-entityid"
									},
									"datatype": "wikibase-item"
								}
							]
						},
						"snaks-order": [
							"P248"
						]
					}
				]
			}
		],
		"P2518": [
			{
				"mainsnak": {
					"snaktype": "value",
					"property": "P2518",
					"datavalue": {
						"value": "11923",
						"type": "string"
					},
					"datatype": "external-id"
				},
				"type": "statement",
				"id": "Q62721520$cfe6b3af-4bea-fe13-3855-46fe21332255",
				"rank": "normal"
			}
		],
		"P1804": [
			{
				"mainsnak": {
					"snaktype": "value",
					"property": "P1804",
					"datavalue": {
						"value": "115263",
						"type": "string"
					},
					"datatype": "external-id"
				},
				"type": "statement",
				"id": "Q62721520$0b01e0ac-450e-b440-3657-753ecd918f9a",
				"rank": "normal"
			}
		],
		"P5970": [
			{
				"mainsnak": {
					"snaktype": "value",
					"property": "P5970",
					"datavalue": {
						"value": {
							"entity-type": "item",
							"numeric-id": 56887761,
							"id": "Q56887761"
						},
						"type": "wikibase-entityid"
					},
					"datatype": "wikibase-item"
				},
				"type": "statement",
				"id": "Q62721520$479dd6c9-4081-1547-3c72-7c1298459194",
				"rank": "normal"
			}
		],
		"P3306": [
			{
				"mainsnak": {
					"snaktype": "value",
					"property": "P3306",
					"datavalue": {
						"value": {
							"entity-type": "item",
							"numeric-id": 27253945,
							"id": "Q27253945"
						},
						"type": "wikibase-entityid"
					},
					"datatype": "wikibase-item"
				},
				"type": "statement",
				"id": "Q62721520$C9058AFF-DDAD-476E-B26B-8FE268883A54",
				"rank": "normal",
				"references": [
					{
						"hash": "f1b1da8d8475b34e65bf0185c1ad04eb7270d17b",
						"snaks": {
							"P854": [
								{
									"snaktype": "value",
									"property": "P854",
									"datavalue": {
										"value": "https://sede.mcu.gob.es/webicaa/Ficheros/145619/34/145619/1/209.pdf",
										"type": "string"
									},
									"datatype": "url"
								}
							]
						},
						"snaks-order": [
							"P854"
						]
					}
				]
			}
		],
		"P5128": [
			{
				"mainsnak": {
					"snaktype": "value",
					"property": "P5128",
					"datavalue": {
						"value": "145619",
						"type": "string"
					},
					"datatype": "external-id"
				},
				"type": "statement",
				"id": "Q62721520$7B218AC8-3605-4916-B888-A8DB402B0549",
				"rank": "normal"
			}
		],
		"P2047": [
			{
				"mainsnak": {
					"snaktype": "value",
					"property": "P2047",
					"datavalue": {
						"value": {
							"amount": "+119",
							"unit": "http://www.wikidata.org/entity/Q7727"
						},
						"type": "quantity"
					},
					"datatype": "quantity"
				},
				"type": "statement",
				"id": "Q62721520$f1236eef-4925-40be-439a-636c262157eb",
				"rank": "normal",
				"references": [
					{
						"hash": "d94d6cb4b672e897f7877d3610224541c265648e",
						"snaks": {
							"P143": [
								{
									"snaktype": "value",
									"property": "P143",
									"datavalue": {
										"value": {
											"entity-type": "item",
											"numeric-id": 206855,
											"id": "Q206855"
										},
										"type": "wikibase-entityid"
									},
									"datatype": "wikibase-item"
								}
							],
							"P4656": [
								{
									"snaktype": "value",
									"property": "P4656",
									"datavalue": {
										"value": "https://ru.wikipedia.org/?oldid=104434301",
										"type": "string"
									},
									"datatype": "url"
								}
							]
						},
						"snaks-order": [
							"P143",
							"P4656"
						]
					}
				]
			}
		],
		"P2346": [
			{
				"mainsnak": {
					"snaktype": "value",
					"property": "P2346",
					"datavalue": {
						"value": "1612044",
						"type": "string"
					},
					"datatype": "external-id"
				},
				"type": "statement",
				"id": "Q62721520$355179df-4444-e54f-b187-8f920a4a4234",
				"rank": "normal"
			}
		],
		"P4665": [
			{
				"mainsnak": {
					"snaktype": "value",
					"property": "P4665",
					"datavalue": {
						"value": "2611119",
						"type": "string"
					},
					"datatype": "external-id"
				},
				"type": "statement",
				"id": "Q62721520$9d95dd4f-4ec3-92ca-7c0e-164ad74eaa74",
				"rank": "normal"
			}
		],
		"P2363": [
			{
				"mainsnak": {
					"snaktype": "value",
					"property": "P2363",
					"datavalue": {
						"value": {
							"entity-type": "item",
							"numeric-id": 21571489,
							"id": "Q21571489"
						},
						"type": "wikibase-entityid"
					},
					"datatype": "wikibase-item"
				},
				"type": "statement",
				"qualifiers": {
					"P2676": [
						{
							"snaktype": "value",
							"property": "P2676",
							"hash": "85aeab3a257aa0768878d6d576b75420977b2918",
							"datavalue": {
								"value": "NFT/25494/2019",
								"type": "string"
							},
							"datatype": "string"
						}
					]
				},
				"qualifiers-order": [
					"P2676"
				],
				"id": "Q62721520$5CA27BCC-3AE0-45D9-9DA7-79CFFBB5012C",
				"rank": "normal"
			}
		],
		"P166": [
			{
				"mainsnak": {
					"snaktype": "value",
					"property": "P166",
					"datavalue": {
						"value": {
							"entity-type": "item",
							"numeric-id": 1011509,
							"id": "Q1011509"
						},
						"type": "wikibase-entityid"
					},
					"datatype": "wikibase-item"
				},
				"type": "statement",
				"qualifiers": {
					"P585": [
						{
							"snaktype": "value",
							"property": "P585",
							"hash": "09f85c089438e099c1cd33998f5c59a57729afd2",
							"datavalue": {
								"value": {
									"time": "+2020-00-00T00:00:00Z",
									"timezone": 0,
									"before": 0,
									"after": 0,
									"precision": 9,
									"calendarmodel": "http://www.wikidata.org/entity/Q1985727"
								},
								"type": "time"
							},
							"datatype": "time"
						}
					]
				},
				"qualifiers-order": [
					"P585"
				],
				"id": "Q62721520$9c17b0a6-44c3-8150-fdf6-c2c21ef95399",
				"rank": "normal",
				"references": [
					{
						"hash": "50233ffed285d899f43ed761c32ffb03f1d2ce19",
						"snaks": {
							"P854": [
								{
									"snaktype": "value",
									"property": "P854",
									"datavalue": {
										"value": "https://www.cnet.com/google-amp/news/golden-globes-2020-all-the-winners-from-last-night-joker-chernobyl-joaquin-phoenix/",
										"type": "string"
									},
									"datatype": "url"
								}
							],
							"P813": [
								{
									"snaktype": "value",
									"property": "P813",
									"datavalue": {
										"value": {
											"time": "+2020-01-25T00:00:00Z",
											"timezone": 0,
											"before": 0,
											"after": 0,
											"precision": 11,
											"calendarmodel": "http://www.wikidata.org/entity/Q1985727"
										},
										"type": "time"
									},
									"datatype": "time"
								}
							],
							"P1476": [
								{
									"snaktype": "value",
									"property": "P1476",
									"datavalue": {
										"value": {
											"text": "Golden Globes 2020: All the winners from last night",
											"language": "en"
										},
										"type": "monolingualtext"
									},
									"datatype": "monolingualtext"
								}
							],
							"P2093": [
								{
									"snaktype": "value",
									"property": "P2093",
									"datavalue": {
										"value": "Jennifer Bisset",
										"type": "string"
									},
									"datatype": "string"
								}
							],
							"P407": [
								{
									"snaktype": "value",
									"property": "P407",
									"datavalue": {
										"value": {
											"entity-type": "item",
											"numeric-id": 1860,
											"id": "Q1860"
										},
										"type": "wikibase-entityid"
									},
									"datatype": "wikibase-item"
								}
							]
						},
						"snaks-order": [
							"P854",
							"P813",
							"P1476",
							"P2093",
							"P407"
						]
					}
				]
			},
			{
				"mainsnak": {
					"snaktype": "value",
					"property": "P166",
					"datavalue": {
						"value": {
							"entity-type": "item",
							"numeric-id": 586356,
							"id": "Q586356"
						},
						"type": "wikibase-entityid"
					},
					"datatype": "wikibase-item"
				},
				"type": "statement",
				"qualifiers": {
					"P585": [
						{
							"snaktype": "value",
							"property": "P585",
							"hash": "09f85c089438e099c1cd33998f5c59a57729afd2",
							"datavalue": {
								"value": {
									"time": "+2020-00-00T00:00:00Z",
									"timezone": 0,
									"before": 0,
									"after": 0,
									"precision": 9,
									"calendarmodel": "http://www.wikidata.org/entity/Q1985727"
								},
								"type": "time"
							},
							"datatype": "time"
						}
					]
				},
				"qualifiers-order": [
					"P585"
				],
				"id": "Q62721520$fb0eb1ed-4e8a-0694-b08f-5c15f345a25a",
				"rank": "normal",
				"references": [
					{
						"hash": "50233ffed285d899f43ed761c32ffb03f1d2ce19",
						"snaks": {
							"P854": [
								{
									"snaktype": "value",
									"property": "P854",
									"datavalue": {
										"value": "https://www.cnet.com/google-amp/news/golden-globes-2020-all-the-winners-from-last-night-joker-chernobyl-joaquin-phoenix/",
										"type": "string"
									},
									"datatype": "url"
								}
							],
							"P813": [
								{
									"snaktype": "value",
									"property": "P813",
									"datavalue": {
										"value": {
											"time": "+2020-01-25T00:00:00Z",
											"timezone": 0,
											"before": 0,
											"after": 0,
											"precision": 11,
											"calendarmodel": "http://www.wikidata.org/entity/Q1985727"
										},
										"type": "time"
									},
									"datatype": "time"
								}
							],
							"P1476": [
								{
									"snaktype": "value",
									"property": "P1476",
									"datavalue": {
										"value": {
											"text": "Golden Globes 2020: All the winners from last night",
											"language": "en"
										},
										"type": "monolingualtext"
									},
									"datatype": "monolingualtext"
								}
							],
							"P2093": [
								{
									"snaktype": "value",
									"property": "P2093",
									"datavalue": {
										"value": "Jennifer Bisset",
										"type": "string"
									},
									"datatype": "string"
								}
							],
							"P407": [
								{
									"snaktype": "value",
									"property": "P407",
									"datavalue": {
										"value": {
											"entity-type": "item",
											"numeric-id": 1860,
											"id": "Q1860"
										},
										"type": "wikibase-entityid"
									},
									"datatype": "wikibase-item"
								}
							]
						},
						"snaks-order": [
							"P854",
							"P813",
							"P1476",
							"P2093",
							"P407"
						]
					}
				]
			},
			{
				"mainsnak": {
					"snaktype": "value",
					"property": "P166",
					"datavalue": {
						"value": {
							"entity-type": "item",
							"numeric-id": 830079,
							"id": "Q830079"
						},
						"type": "wikibase-entityid"
					},
					"datatype": "wikibase-item"
				},
				"type": "statement",
				"qualifiers": {
					"P585": [
						{
							"snaktype": "value",
							"property": "P585",
							"hash": "09f85c089438e099c1cd33998f5c59a57729afd2",
							"datavalue": {
								"value": {
									"time": "+2020-00-00T00:00:00Z",
									"timezone": 0,
									"before": 0,
									"after": 0,
									"precision": 9,
									"calendarmodel": "http://www.wikidata.org/entity/Q1985727"
								},
								"type": "time"
							},
							"datatype": "time"
						}
					],
					"P805": [
						{
							"snaktype": "value",
							"property": "P805",
							"hash": "a16cdb2e16c5b3c990176038cb0f18945e61a570",
							"datavalue": {
								"value": {
									"entity-type": "item",
									"numeric-id": 47496499,
									"id": "Q47496499"
								},
								"type": "wikibase-entityid"
							},
							"datatype": "wikibase-item"
						}
					],
					"P155": [
						{
							"snaktype": "value",
							"property": "P155",
							"hash": "08d238aba8ed149e48e706f1eaf9377c1474ef42",
							"datavalue": {
								"value": {
									"entity-type": "item",
									"numeric-id": 27894574,
									"id": "Q27894574"
								},
								"type": "wikibase-entityid"
							},
							"datatype": "wikibase-item"
						}
					],
					"P1346": [
						{
							"snaktype": "value",
							"property": "P1346",
							"hash": "693609c34773c01c0dab65af2e24e665a710f1fb",
							"datavalue": {
								"value": {
									"entity-type": "item",
									"numeric-id": 16751422,
									"id": "Q16751422"
								},
								"type": "wikibase-entityid"
							},
							"datatype": "wikibase-item"
						},
						{
							"snaktype": "value",
							"property": "P1346",
							"hash": "25c842b39c9e360e3bf6749adf707fbfe36aa262",
							"datavalue": {
								"value": {
									"entity-type": "item",
									"numeric-id": 15849487,
									"id": "Q15849487"
								},
								"type": "wikibase-entityid"
							},
							"datatype": "wikibase-item"
						}
					]
				},
				"qualifiers-order": [
					"P585",
					"P805",
					"P155",
					"P1346"
				],
				"id": "Q62721520$51eb2d77-4722-680e-24fb-a4d9348040ef",
				"rank": "normal"
			},
			{
				"mainsnak": {
					"snaktype": "value",
					"property": "P166",
					"datavalue": {
						"value": {
							"entity-type": "item",
							"numeric-id": 131520,
							"id": "Q131520"
						},
						"type": "wikibase-entityid"
					},
					"datatype": "wikibase-item"
				},
				"type": "statement",
				"qualifiers": {
					"P585": [
						{
							"snaktype": "value",
							"property": "P585",
							"hash": "09f85c089438e099c1cd33998f5c59a57729afd2",
							"datavalue": {
								"value": {
									"time": "+2020-00-00T00:00:00Z",
									"timezone": 0,
									"before": 0,
									"after": 0,
									"precision": 9,
									"calendarmodel": "http://www.wikidata.org/entity/Q1985727"
								},
								"type": "time"
							},
							"datatype": "time"
						}
					],
					"P805": [
						{
							"snaktype": "value",
							"property": "P805",
							"hash": "a16cdb2e16c5b3c990176038cb0f18945e61a570",
							"datavalue": {
								"value": {
									"entity-type": "item",
									"numeric-id": 47496499,
									"id": "Q47496499"
								},
								"type": "wikibase-entityid"
							},
							"datatype": "wikibase-item"
						}
					],
					"P155": [
						{
							"snaktype": "value",
							"property": "P155",
							"hash": "da812ae3315b2f25d7be18880c11922773f48de7",
							"datavalue": {
								"value": {
									"entity-type": "item",
									"numeric-id": 27959455,
									"id": "Q27959455"
								},
								"type": "wikibase-entityid"
							},
							"datatype": "wikibase-item"
						}
					],
					"P1346": [
						{
							"snaktype": "value",
							"property": "P1346",
							"hash": "d370eeeb0661567a8699d54058e0639c19b40325",
							"datavalue": {
								"value": {
									"entity-type": "item",
									"numeric-id": 460277,
									"id": "Q460277"
								},
								"type": "wikibase-entityid"
							},
							"datatype": "wikibase-item"
						}
					]
				},
				"qualifiers-order": [
					"P585",
					"P805",
					"P155",
					"P1346"
				],
				"id": "Q62721520$f7dd1080-4720-194d-d44d-9fc5f9353f50",
				"rank": "normal"
			},
			{
				"mainsnak": {
					"snaktype": "value",
					"property": "P166",
					"datavalue": {
						"value": {
							"entity-type": "item",
							"numeric-id": 393686,
							"id": "Q393686"
						},
						"type": "wikibase-entityid"
					},
					"datatype": "wikibase-item"
				},
				"type": "statement",
				"qualifiers": {
					"P585": [
						{
							"snaktype": "value",
							"property": "P585",
							"hash": "09f85c089438e099c1cd33998f5c59a57729afd2",
							"datavalue": {
								"value": {
									"time": "+2020-00-00T00:00:00Z",
									"timezone": 0,
									"before": 0,
									"after": 0,
									"precision": 9,
									"calendarmodel": "http://www.wikidata.org/entity/Q1985727"
								},
								"type": "time"
							},
							"datatype": "time"
						}
					],
					"P805": [
						{
							"snaktype": "value",
							"property": "P805",
							"hash": "a16cdb2e16c5b3c990176038cb0f18945e61a570",
							"datavalue": {
								"value": {
									"entity-type": "item",
									"numeric-id": 47496499,
									"id": "Q47496499"
								},
								"type": "wikibase-entityid"
							},
							"datatype": "wikibase-item"
						}
					],
					"P1346": [
						{
							"snaktype": "value",
							"property": "P1346",
							"hash": "4b275751fa9686dcc7e2833431769597ab3f7daa",
							"datavalue": {
								"value": {
									"entity-type": "item",
									"numeric-id": 15818581,
									"id": "Q15818581"
								},
								"type": "wikibase-entityid"
							},
							"datatype": "wikibase-item"
						},
						{
							"snaktype": "value",
							"property": "P1346",
							"hash": "31b2c8ca2f767a44b9e067fbfd51e667dbc70b26",
							"datavalue": {
								"value": {
									"entity-type": "item",
									"numeric-id": 1544876,
									"id": "Q1544876"
								},
								"type": "wikibase-entityid"
							},
							"datatype": "wikibase-item"
						},
						{
							"snaktype": "value",
							"property": "P1346",
							"hash": "9c894cc53e627a0ca28e89a27ae89af782aba5fc",
							"datavalue": {
								"value": {
									"entity-type": "item",
									"numeric-id": 61721586,
									"id": "Q61721586"
								},
								"type": "wikibase-entityid"
							},
							"datatype": "wikibase-item"
						}
					],
					"P155": [
						{
							"snaktype": "value",
							"property": "P155",
							"hash": "881690212aadbb1836d162d291ebb1eba8a5089c",
							"datavalue": {
								"value": {
									"entity-type": "item",
									"numeric-id": 42708010,
									"id": "Q42708010"
								},
								"type": "wikibase-entityid"
							},
							"datatype": "wikibase-item"
						}
					]
				},
				"qualifiers-order": [
					"P585",
					"P805",
					"P1346",
					"P155"
				],
				"id": "Q62721520$9f2c5464-4f7d-da71-78c2-bb8f949d927e",
				"rank": "normal"
			}
		],
		"P5150": [
			{
				"mainsnak": {
					"snaktype": "value",
					"property": "P5150",
					"datavalue": {
						"value": {
							"entity-type": "item",
							"numeric-id": 52692412,
							"id": "Q52692412"
						},
						"type": "wikibase-entityid"
					},
					"datatype": "wikibase-item"
				},
				"type": "statement",
				"qualifiers": {
					"P2676": [
						{
							"snaktype": "value",
							"property": "P2676",
							"hash": "979175bdfb3b5d22ed09a7e083188d8ffe86f628",
							"datavalue": {
								"value": "60/2020",
								"type": "string"
							},
							"datatype": "string"
						}
					]
				},
				"qualifiers-order": [
					"P2676"
				],
				"id": "Q62721520$9FE3D9A7-193F-474B-9FAC-1D631D0A3952",
				"rank": "normal"
			}
		],
		"P2758": [
			{
				"mainsnak": {
					"snaktype": "value",
					"property": "P2758",
					"datavalue": {
						"value": {
							"entity-type": "item",
							"numeric-id": 23817729,
							"id": "Q23817729"
						},
						"type": "wikibase-entityid"
					},
					"datatype": "wikibase-item"
				},
				"type": "statement",
				"id": "Q62721520$A1BD554A-992A-4602-86D5-86EDEA357104",
				"rank": "normal",
				"references": [
					{
						"hash": "5f3a88ec411401d860ec47423aa8d605ec1bf5c0",
						"snaks": {
							"P854": [
								{
									"snaktype": "value",
									"property": "P854",
									"datavalue": {
										"value": "https://www.cnc.fr/professionnels/visas-et-classification/152284",
										"type": "string"
									},
									"datatype": "url"
								}
							]
						},
						"snaks-order": [
							"P854"
						]
					}
				]
			},
			{
				"mainsnak": {
					"snaktype": "value",
					"property": "P2758",
					"datavalue": {
						"value": {
							"entity-type": "item",
							"numeric-id": 23817739,
							"id": "Q23817739"
						},
						"type": "wikibase-entityid"
					},
					"datatype": "wikibase-item"
				},
				"type": "statement",
				"id": "Q62721520$4FE3A0EE-6656-48B8-AD8D-752378365B77",
				"rank": "normal",
				"references": [
					{
						"hash": "5f3a88ec411401d860ec47423aa8d605ec1bf5c0",
						"snaks": {
							"P854": [
								{
									"snaktype": "value",
									"property": "P854",
									"datavalue": {
										"value": "https://www.cnc.fr/professionnels/visas-et-classification/152284",
										"type": "string"
									},
									"datatype": "url"
								}
							]
						},
						"snaks-order": [
							"P854"
						]
					}
				]
			}
		],
		"P2755": [
			{
				"mainsnak": {
					"snaktype": "value",
					"property": "P2755",
					"datavalue": {
						"value": "152284",
						"type": "string"
					},
					"datatype": "external-id"
				},
				"type": "statement",
				"qualifiers": {
					"P580": [
						{
							"snaktype": "value",
							"property": "P580",
							"hash": "f5f7f091c4a9f6c8f542f05227e20f14042fdab0",
							"datavalue": {
								"value": {
									"time": "+2020-01-14T00:00:00Z",
									"timezone": 0,
									"before": 0,
									"after": 0,
									"precision": 11,
									"calendarmodel": "http://www.wikidata.org/entity/Q1985727"
								},
								"type": "time"
							},
							"datatype": "time"
						}
					]
				},
				"qualifiers-order": [
					"P580"
				],
				"id": "Q62721520$6C9E8D64-171E-4999-8602-4471CF8BDBDC",
				"rank": "normal"
			}
		],
		"P1562": [
			{
				"mainsnak": {
					"snaktype": "value",
					"property": "P1562",
					"datavalue": {
						"value": "v718464",
						"type": "string"
					},
					"datatype": "external-id"
				},
				"type": "statement",
				"id": "Q62721520$ccf4ea1f-4008-1c2d-a89c-fb1fa11f8e66",
				"rank": "normal"
			}
		],
		"P1258": [
			{
				"mainsnak": {
					"snaktype": "value",
					"property": "P1258",
					"datavalue": {
						"value": "m/1917_2019",
						"type": "string"
					},
					"datatype": "external-id"
				},
				"type": "statement",
				"id": "Q62721520$482c8e65-4fa6-6a4c-4197-9f24ec8fa070",
				"rank": "normal"
			}
		],
		"P1712": [
			{
				"mainsnak": {
					"snaktype": "value",
					"property": "P1712",
					"datavalue": {
						"value": "movie/1917",
						"type": "string"
					},
					"datatype": "external-id"
				},
				"type": "statement",
				"id": "Q62721520$17dee3f2-4f6b-10d3-d38c-fb5508b2dffb",
				"rank": "normal"
			}
		],
		"P3808": [
			{
				"mainsnak": {
					"snaktype": "value",
					"property": "P3808",
					"datavalue": {
						"value": "1917-(2019)",
						"type": "string"
					},
					"datatype": "external-id"
				},
				"type": "statement",
				"id": "Q62721520$95efa5fc-400a-8900-8f4e-e85a1b6b8781",
				"rank": "normal"
			}
		],
		"P1237": [
			{
				"mainsnak": {
					"snaktype": "value",
					"property": "P1237",
					"datavalue": {
						"value": "1917",
						"type": "string"
					},
					"datatype": "external-id"
				},
				"type": "statement",
				"id": "Q62721520$c7542696-4432-d683-811e-c5866de3c747",
				"rank": "normal"
			}
		],
		"P2529": [
			{
				"mainsnak": {
					"snaktype": "value",
					"property": "P2529",
					"datavalue": {
						"value": "708117",
						"type": "string"
					},
					"datatype": "external-id"
				},
				"type": "statement",
				"id": "Q62721520$fbf7ea63-4047-a3f5-8a3e-892b4c58189a",
				"rank": "normal"
			}
		],
		"P4437": [
			{
				"mainsnak": {
					"snaktype": "value",
					"property": "P4437",
					"datavalue": {
						"value": {
							"entity-type": "item",
							"numeric-id": 42012503,
							"id": "Q42012503"
						},
						"type": "wikibase-entityid"
					},
					"datatype": "wikibase-item"
				},
				"type": "statement",
				"qualifiers": {
					"P7367": [
						{
							"snaktype": "value",
							"property": "P7367",
							"hash": "c245d85df57fbc58ca5690274bc39e169d365267",
							"datavalue": {
								"value": {
									"entity-type": "item",
									"numeric-id": 73387803,
									"id": "Q73387803"
								},
								"type": "wikibase-entityid"
							},
							"datatype": "wikibase-item"
						},
						{
							"snaktype": "value",
							"property": "P7367",
							"hash": "8d735ba0fcdcb689bdc4c9e23b5b4d3b7884612a",
							"datavalue": {
								"value": {
									"entity-type": "item",
									"numeric-id": 73387816,
									"id": "Q73387816"
								},
								"type": "wikibase-entityid"
							},
							"datatype": "wikibase-item"
						}
					]
				},
				"qualifiers-order": [
					"P7367"
				],
				"id": "Q62721520$854EB051-4FFA-437D-ABE2-6312F021C319",
				"rank": "normal",
				"references": [
					{
						"hash": "7a466c94708742ba183ce3bc70202567d92795b4",
						"snaks": {
							"P854": [
								{
									"snaktype": "value",
									"property": "P854",
									"datavalue": {
										"value": "http://fpbquery.fpb.org.za/erms/film_details.aspx?ref=83611",
										"type": "string"
									},
									"datatype": "url"
								}
							]
						},
						"snaks-order": [
							"P854"
						]
					}
				]
			}
		],
		"P3402": [
			{
				"mainsnak": {
					"snaktype": "value",
					"property": "P3402",
					"datavalue": {
						"value": {
							"entity-type": "item",
							"numeric-id": 27915575,
							"id": "Q27915575"
						},
						"type": "wikibase-entityid"
					},
					"datatype": "wikibase-item"
				},
				"type": "statement",
				"qualifiers": {
					"P2676": [
						{
							"snaktype": "value",
							"property": "P2676",
							"hash": "34fe79c2c44fd86d10af9da8b302f858a349f6a1",
							"datavalue": {
								"value": "16064",
								"type": "string"
							},
							"datatype": "string"
						}
					]
				},
				"qualifiers-order": [
					"P2676"
				],
				"id": "Q62721520$29D2B8B8-F570-45A9-9E87-A1466D2D0A1B",
				"rank": "normal",
				"references": [
					{
						"hash": "dc5587af6f99903f971ddcc5875d87b4ff0c5d92",
						"snaks": {
							"P854": [
								{
									"snaktype": "value",
									"property": "P854",
									"datavalue": {
										"value": "http://cnc.abt.ro/registru/index.aspx?pageID=3&filmID=16288",
										"type": "string"
									},
									"datatype": "url"
								}
							]
						},
						"snaks-order": [
							"P854"
						]
					}
				]
			}
		],
		"P18": [
			{
				"mainsnak": {
					"snaktype": "value",
					"property": "P18",
					"datavalue": {
						"value": "1917logo.svg",
						"type": "string"
					},
					"datatype": "commonsMedia"
				},
				"type": "statement",
				"id": "Q62721520$111777b3-4a77-2c16-1a18-d907e943255f",
				"rank": "normal"
			}
		],
		"P6658": [
			{
				"mainsnak": {
					"snaktype": "value",
					"property": "P6658",
					"datavalue": {
						"value": {
							"entity-type": "item",
							"numeric-id": 62371961,
							"id": "Q62371961"
						},
						"type": "wikibase-entityid"
					},
					"datatype": "wikibase-item"
				},
				"type": "statement",
				"qualifiers": {
					"P2676": [
						{
							"snaktype": "value",
							"property": "P2676",
							"hash": "035e12df3507069944c44a11d8620055513caf0d",
							"datavalue": {
								"value": "419032",
								"type": "string"
							},
							"datatype": "string"
						}
					]
				},
				"qualifiers-order": [
					"P2676"
				],
				"id": "Q62721520$7695BEB2-6C64-4F74-A7EC-D1B4D2D12E5D",
				"rank": "normal",
				"references": [
					{
						"hash": "0a39f9059382cadf4f2a5aff7f6083ad44fcd0d7",
						"snaks": {
							"P854": [
								{
									"snaktype": "value",
									"property": "P854",
									"datavalue": {
										"value": "https://www.rcq.gouv.qc.ca/RCQ212AfficherFicheTech.asp?intNoFilm=419032",
										"type": "string"
									},
									"datatype": "url"
								}
							]
						},
						"snaks-order": [
							"P854"
						]
					}
				]
			}
		],
		"P5990": [
			{
				"mainsnak": {
					"snaktype": "value",
					"property": "P5990",
					"datavalue": {
						"value": "1917-2019",
						"type": "string"
					},
					"datatype": "external-id"
				},
				"type": "statement",
				"id": "Q62721520$E08EB4CF-8F75-41A1-9300-EDA9F16F6795",
				"rank": "normal"
			}
		],
		"P4632": [
			{
				"mainsnak": {
					"snaktype": "value",
					"property": "P4632",
					"datavalue": {
						"value": "8962",
						"type": "string"
					},
					"datatype": "external-id"
				},
				"type": "statement",
				"id": "Q62721520$EB36322A-6C34-4948-BCD6-72114ABD12BA",
				"rank": "normal"
			}
		],
		"P8033": [
			{
				"mainsnak": {
					"snaktype": "value",
					"property": "P8033",
					"datavalue": {
						"value": "1917-m100129468",
						"type": "string"
					},
					"datatype": "external-id"
				},
				"type": "statement",
				"id": "Q62721520$70878CE9-C323-4FA4-AA76-A281F04F3695",
				"rank": "normal"
			}
		],
		"P1552": [
			{
				"mainsnak": {
					"snaktype": "value",
					"property": "P1552",
					"datavalue": {
						"value": {
							"entity-type": "item",
							"numeric-id": 45172088,
							"id": "Q45172088"
						},
						"type": "wikibase-entityid"
					},
					"datatype": "wikibase-item"
				},
				"type": "statement",
				"qualifiers": {
					"P1013": [
						{
							"snaktype": "value",
							"property": "P1013",
							"hash": "30ddffb176643f466e76c3a0164abeafb1bc7b37",
							"datavalue": {
								"value": {
									"entity-type": "item",
									"numeric-id": 93591279,
									"id": "Q93591279"
								},
								"type": "wikibase-entityid"
							},
							"datatype": "wikibase-item"
						}
					]
				},
				"qualifiers-order": [
					"P1013"
				],
				"id": "Q62721520$d14cfe75-4e3f-ca2a-5118-39da2d811829",
				"rank": "normal",
				"references": [
					{
						"hash": "1e7c2864b7187d6ccda9c2dad5d8b89db79783b6",
						"snaks": {
							"P248": [
								{
									"snaktype": "value",
									"property": "P248",
									"datavalue": {
										"value": {
											"entity-type": "item",
											"numeric-id": 45150204,
											"id": "Q45150204"
										},
										"type": "wikibase-entityid"
									},
									"datatype": "wikibase-item"
								}
							],
							"P4632": [
								{
									"snaktype": "value",
									"property": "P4632",
									"datavalue": {
										"value": "8962",
										"type": "string"
									},
									"datatype": "external-id"
								}
							],
							"P813": [
								{
									"snaktype": "value",
									"property": "P813",
									"datavalue": {
										"value": {
											"time": "+2020-05-12T00:00:00Z",
											"timezone": 0,
											"before": 0,
											"after": 0,
											"precision": 11,
											"calendarmodel": "http://www.wikidata.org/entity/Q1985727"
										},
										"type": "time"
									},
									"datatype": "time"
								}
							]
						},
						"snaks-order": [
							"P248",
							"P4632",
							"P813"
						]
					}
				]
			},
			{
				"mainsnak": {
					"snaktype": "value",
					"property": "P1552",
					"datavalue": {
						"value": {
							"entity-type": "item",
							"numeric-id": 58483045,
							"id": "Q58483045"
						},
						"type": "wikibase-entityid"
					},
					"datatype": "wikibase-item"
				},
				"type": "statement",
				"qualifiers": {
					"P1013": [
						{
							"snaktype": "value",
							"property": "P1013",
							"hash": "30ddffb176643f466e76c3a0164abeafb1bc7b37",
							"datavalue": {
								"value": {
									"entity-type": "item",
									"numeric-id": 93591279,
									"id": "Q93591279"
								},
								"type": "wikibase-entityid"
							},
							"datatype": "wikibase-item"
						}
					]
				},
				"qualifiers-order": [
					"P1013"
				],
				"id": "Q62721520$6f97e224-4157-6807-b388-7944a3a9ef8a",
				"rank": "normal",
				"references": [
					{
						"hash": "08c5b572b311f42aa52ae8868cb93b87be80f020",
						"snaks": {
							"P248": [
								{
									"snaktype": "value",
									"property": "P248",
									"datavalue": {
										"value": {
											"entity-type": "item",
											"numeric-id": 62721520,
											"id": "Q62721520"
										},
										"type": "wikibase-entityid"
									},
									"datatype": "wikibase-item"
								}
							]
						},
						"snaks-order": [
							"P248"
						]
					}
				]
			},
			{
				"mainsnak": {
					"snaktype": "value",
					"property": "P1552",
					"datavalue": {
						"value": {
							"entity-type": "item",
							"numeric-id": 93770083,
							"id": "Q93770083"
						},
						"type": "wikibase-entityid"
					},
					"datatype": "wikibase-item"
				},
				"type": "statement",
				"id": "Q62721520$a3bc7a40-4381-ec8e-62b5-396ef5c026ea",
				"rank": "normal",
				"references": [
					{
						"hash": "08c5b572b311f42aa52ae8868cb93b87be80f020",
						"snaks": {
							"P248": [
								{
									"snaktype": "value",
									"property": "P248",
									"datavalue": {
										"value": {
											"entity-type": "item",
											"numeric-id": 62721520,
											"id": "Q62721520"
										},
										"type": "wikibase-entityid"
									},
									"datatype": "wikibase-item"
								}
							]
						},
						"snaks-order": [
							"P248"
						]
					}
				]
			},
			{
				"mainsnak": {
					"snaktype": "value",
					"property": "P1552",
					"datavalue": {
						"value": {
							"entity-type": "item",
							"numeric-id": 93985027,
							"id": "Q93985027"
						},
						"type": "wikibase-entityid"
					},
					"datatype": "wikibase-item"
				},
				"type": "statement",
				"id": "Q62721520$4d554739-4989-35b3-df5e-da5452d7f5c7",
				"rank": "normal",
				"references": [
					{
						"hash": "08c5b572b311f42aa52ae8868cb93b87be80f020",
						"snaks": {
							"P248": [
								{
									"snaktype": "value",
									"property": "P248",
									"datavalue": {
										"value": {
											"entity-type": "item",
											"numeric-id": 62721520,
											"id": "Q62721520"
										},
										"type": "wikibase-entityid"
									},
									"datatype": "wikibase-item"
								}
							]
						},
						"snaks-order": [
							"P248"
						]
					}
				]
			}
		]
	},
	"sitelinks": {
		"arwiki": {
			"site": "arwiki",
			"title": "1917 (فيلم 2019)",
			"badges": [],
			"url": "https://ar.wikipedia.org/wiki/1917_(%D9%81%D9%8A%D9%84%D9%85_2019)"
		},
		"azwiki": {
			"site": "azwiki",
			"title": "1917 (film, 2019)",
			"badges": [],
			"url": "https://az.wikipedia.org/wiki/1917_(film,_2019)"
		},
		"be_x_oldwiki": {
			"site": "be_x_oldwiki",
			"title": "1917 (фільм)",
			"badges": [],
			"url": "https://be-tarask.wikipedia.org/wiki/1917_(%D1%84%D1%96%D0%BB%D1%8C%D0%BC)"
		},
		"bewiki": {
			"site": "bewiki",
			"title": "1917 (фільм, 2019)",
			"badges": [],
			"url": "https://be.wikipedia.org/wiki/1917_(%D1%84%D1%96%D0%BB%D1%8C%D0%BC,_2019)"
		},
		"bnwiki": {
			"site": "bnwiki",
			"title": "নাইনটিন সেভেনটিন (২০১৯-এর চলচ্চিত্র)",
			"badges": [],
			"url": "https://bn.wikipedia.org/wiki/%E0%A6%A8%E0%A6%BE%E0%A6%87%E0%A6%A8%E0%A6%9F%E0%A6%BF%E0%A6%A8_%E0%A6%B8%E0%A7%87%E0%A6%AD%E0%A7%87%E0%A6%A8%E0%A6%9F%E0%A6%BF%E0%A6%A8_(%E0%A7%A8%E0%A7%A6%E0%A7%A7%E0%A7%AF-%E0%A6%8F%E0%A6%B0_%E0%A6%9A%E0%A6%B2%E0%A6%9A%E0%A7%8D%E0%A6%9A%E0%A6%BF%E0%A6%A4%E0%A7%8D%E0%A6%B0)"
		},
		"cawiki": {
			"site": "cawiki",
			"title": "1917 (pel·lícula)",
			"badges": [],
			"url": "https://ca.wikipedia.org/wiki/1917_(pel%C2%B7l%C3%ADcula)"
		},
		"ckbwiki": {
			"site": "ckbwiki",
			"title": "١٩١٧ (فیلمی ٢٠١٩)",
			"badges": [],
			"url": "https://ckb.wikipedia.org/wiki/%D9%A1%D9%A9%D9%A1%D9%A7_(%D9%81%DB%8C%D9%84%D9%85%DB%8C_%D9%A2%D9%A0%D9%A1%D9%A9)"
		},
		"cswiki": {
			"site": "cswiki",
			"title": "1917 (film, 2019)",
			"badges": [],
			"url": "https://cs.wikipedia.org/wiki/1917_(film,_2019)"
		},
		"dawiki": {
			"site": "dawiki",
			"title": "1917 (film)",
			"badges": [],
			"url": "https://da.wikipedia.org/wiki/1917_(film)"
		},
		"dewiki": {
			"site": "dewiki",
			"title": "1917 (Film)",
			"badges": [],
			"url": "https://de.wikipedia.org/wiki/1917_(Film)"
		},
		"elwiki": {
			"site": "elwiki",
			"title": "1917 (ταινία)",
			"badges": [],
			"url": "https://el.wikipedia.org/wiki/1917_(%CF%84%CE%B1%CE%B9%CE%BD%CE%AF%CE%B1)"
		},
		"enwiki": {
			"site": "enwiki",
			"title": "1917 (2019 film)",
			"badges": [],
			"url": "https://en.wikipedia.org/wiki/1917_(2019_film)"
		},
		"enwikiquote": {
			"site": "enwikiquote",
			"title": "1917 (2019 film)",
			"badges": [],
			"url": "https://en.wikiquote.org/wiki/1917_(2019_film)"
		},
		"eswiki": {
			"site": "eswiki",
			"title": "1917 (película)",
			"badges": [],
			"url": "https://es.wikipedia.org/wiki/1917_(pel%C3%ADcula)"
		},
		"euwiki": {
			"site": "euwiki",
			"title": "1917 (filma)",
			"badges": [],
			"url": "https://eu.wikipedia.org/wiki/1917_(filma)"
		},
		"fawiki": {
			"site": "fawiki",
			"title": "۱۹۱۷ (فیلم ۲۰۱۹)",
			"badges": [],
			"url": "https://fa.wikipedia.org/wiki/%DB%B1%DB%B9%DB%B1%DB%B7_(%D9%81%DB%8C%D9%84%D9%85_%DB%B2%DB%B0%DB%B1%DB%B9)"
		},
		"fiwiki": {
			"site": "fiwiki",
			"title": "Taistelulähetit – 1917",
			"badges": [],
			"url": "https://fi.wikipedia.org/wiki/Taistelul%C3%A4hetit_%E2%80%93_1917"
		},
		"frwiki": {
			"site": "frwiki",
			"title": "1917 (film)",
			"badges": [],
			"url": "https://fr.wikipedia.org/wiki/1917_(film)"
		},
		"glwiki": {
			"site": "glwiki",
			"title": "1917 (filme de 2019)",
			"badges": [],
			"url": "https://gl.wikipedia.org/wiki/1917_(filme_de_2019)"
		},
		"hewiki": {
			"site": "hewiki",
			"title": "1917 (סרט, 2019)",
			"badges": [],
			"url": "https://he.wikipedia.org/wiki/1917_(%D7%A1%D7%A8%D7%98,_2019)"
		},
		"hiwiki": {
			"site": "hiwiki",
			"title": "1917 (फ़िल्म)",
			"badges": [],
			"url": "https://hi.wikipedia.org/wiki/1917_(%E0%A4%AB%E0%A4%BC%E0%A4%BF%E0%A4%B2%E0%A5%8D%E0%A4%AE)"
		},
		"hywiki": {
			"site": "hywiki",
			"title": "1917 (ֆիլմ)",
			"badges": [],
			"url": "https://hy.wikipedia.org/wiki/1917_(%D6%86%D5%AB%D5%AC%D5%B4)"
		},
		"idwiki": {
			"site": "idwiki",
			"title": "1917 (film)",
			"badges": [],
			"url": "https://id.wikipedia.org/wiki/1917_(film)"
		},
		"itwiki": {
			"site": "itwiki",
			"title": "1917 (film)",
			"badges": [],
			"url": "https://it.wikipedia.org/wiki/1917_(film)"
		},
		"jawiki": {
			"site": "jawiki",
			"title": "1917 命をかけた伝令",
			"badges": [],
			"url": "https://ja.wikipedia.org/wiki/1917_%E5%91%BD%E3%82%92%E3%81%8B%E3%81%91%E3%81%9F%E4%BC%9D%E4%BB%A4"
		},
		"kowiki": {
			"site": "kowiki",
			"title": "1917 (영화)",
			"badges": [],
			"url": "https://ko.wikipedia.org/wiki/1917_(%EC%98%81%ED%99%94)"
		},
		"lvwiki": {
			"site": "lvwiki",
			"title": "1917 (filma)",
			"badges": [],
			"url": "https://lv.wikipedia.org/wiki/1917_(filma)"
		},
		"nlwiki": {
			"site": "nlwiki",
			"title": "1917 (film)",
			"badges": [],
			"url": "https://nl.wikipedia.org/wiki/1917_(film)"
		},
		"nowiki": {
			"site": "nowiki",
			"title": "1917 (film)",
			"badges": [],
			"url": "https://no.wikipedia.org/wiki/1917_(film)"
		},
		"plwiki": {
			"site": "plwiki",
			"title": "1917 (film)",
			"badges": [],
			"url": "https://pl.wikipedia.org/wiki/1917_(film)"
		},
		"ptwiki": {
			"site": "ptwiki",
			"title": "1917 (filme)",
			"badges": [],
			"url": "https://pt.wikipedia.org/wiki/1917_(filme)"
		},
		"rowiki": {
			"site": "rowiki",
			"title": "1917: Speranță și moarte",
			"badges": [],
			"url": "https://ro.wikipedia.org/wiki/1917:_Speran%C8%9B%C4%83_%C8%99i_moarte"
		},
		"ruwiki": {
			"site": "ruwiki",
			"title": "1917 (фильм)",
			"badges": [],
			"url": "https://ru.wikipedia.org/wiki/1917_(%D1%84%D0%B8%D0%BB%D1%8C%D0%BC)"
		},
		"ruwikinews": {
			"site": "ruwikinews",
			"title": "Категория:1917 (фильм)",
			"badges": [],
			"url": "https://ru.wikinews.org/wiki/%D0%9A%D0%B0%D1%82%D0%B5%D0%B3%D0%BE%D1%80%D0%B8%D1%8F:1917_(%D1%84%D0%B8%D0%BB%D1%8C%D0%BC)"
		},
		"simplewiki": {
			"site": "simplewiki",
			"title": "1917 (movie)",
			"badges": [],
			"url": "https://simple.wikipedia.org/wiki/1917_(movie)"
		},
		"srwiki": {
			"site": "srwiki",
			"title": "1917 (филм из 2019)",
			"badges": [],
			"url": "https://sr.wikipedia.org/wiki/1917_(%D1%84%D0%B8%D0%BB%D0%BC_%D0%B8%D0%B7_2019)"
		},
		"svwiki": {
			"site": "svwiki",
			"title": "1917 (film)",
			"badges": [],
			"url": "https://sv.wikipedia.org/wiki/1917_(film)"
		},
		"tawiki": {
			"site": "tawiki",
			"title": "1917 (ஆங்கில திரைப்படம்)",
			"badges": [],
			"url": "https://ta.wikipedia.org/wiki/1917_(%E0%AE%86%E0%AE%99%E0%AF%8D%E0%AE%95%E0%AE%BF%E0%AE%B2_%E0%AE%A4%E0%AE%BF%E0%AE%B0%E0%AF%88%E0%AE%AA%E0%AF%8D%E0%AE%AA%E0%AE%9F%E0%AE%AE%E0%AF%8D)"
		},
		"trwiki": {
			"site": "trwiki",
			"title": "1917 (film, 2019)",
			"badges": [],
			"url": "https://tr.wikipedia.org/wiki/1917_(film,_2019)"
		},
		"ukwiki": {
			"site": "ukwiki",
			"title": "1917 (фільм)",
			"badges": [],
			"url": "https://uk.wikipedia.org/wiki/1917_(%D1%84%D1%96%D0%BB%D1%8C%D0%BC)"
		},
		"uzwiki": {
			"site": "uzwiki",
			"title": "1917 (film, 2019)",
			"badges": [],
			"url": "https://uz.wikipedia.org/wiki/1917_(film,_2019)"
		},
		"viwiki": {
			"site": "viwiki",
			"title": "1917 (phim 2019)",
			"badges": [],
			"url": "https://vi.wikipedia.org/wiki/1917_(phim_2019)"
		},
		"zh_yuewiki": {
			"site": "zh_yuewiki",
			"title": "1917：逆戰救兵",
			"badges": [],
			"url": "https://zh-yue.wikipedia.org/wiki/1917%EF%BC%9A%E9%80%86%E6%88%B0%E6%95%91%E5%85%B5"
		},
		"zhwiki": {
			"site": "zhwiki",
			"title": "1917 (電影)",
			"badges": [],
			"url": "https://zh.wikipedia.org/wiki/1917_(%E9%9B%BB%E5%BD%B1)"
		}
	}
}