{"hash":"0bc955b9a2d9abc3c624c4835ad46459cf6742a9","data":{"year":{"title":1918,"events":[{"id":"1-23-tt0430895","title":"Aurore Gagnon's mother, Marie-Anne Caron, dies of tuberculosis","dayofyear":{"path":"/1/23/","month":{"id":"1","title":"January","path":"/month/1/"},"day":{"id":"23","ordinal":"rd"}},"movie":{"id":"tt0430895","path":"/tt0430895/","title":"Aurore","year":2005}},{"id":"4-21-tt0365675","title":"Manfred von Richthofen, the \"Red Baron\", is shot down and killed","dayofyear":{"path":"/4/21/","month":{"id":"4","title":"April","path":"/month/4/"},"day":{"id":"21","ordinal":"st"}},"movie":{"id":"tt0365675","path":"/tt0365675/","title":"The Red Baron","year":2008}},{"id":"7-17-tt0067483","title":"Tsar Nicholas II and his family are killed by Bolsheviks","dayofyear":{"path":"/7/17/","month":{"id":"7","title":"July","path":"/month/7/"},"day":{"id":"17","ordinal":"th"}},"movie":{"id":"tt0067483","path":"/tt0067483/","title":"Nicholas and Alexandra","year":1971}},{"id":"7-17-tt0117442","title":"Tsar Nicholas II and his family are killed by Bolsheviks","dayofyear":{"path":"/7/17/","month":{"id":"7","title":"July","path":"/month/7/"},"day":{"id":"17","ordinal":"th"}},"movie":{"id":"tt0117442","path":"/tt0117442/","title":"Rasputin","year":1996}},{"id":"7-18-tt2304771","title":"Nelson Mandela Day","dayofyear":{"path":"/7/18/","month":{"id":"7","title":"July","path":"/month/7/"},"day":{"id":"18","ordinal":"th"}},"movie":{"id":"tt2304771","path":"/tt2304771/","title":"Mandela: Long Walk to Freedom","year":2013}},{"id":"9-12-tt0018578","title":"Jack Powell and David Armstrong both fight in the Battle of Saint-Mihiel","dayofyear":{"path":"/9/12/","month":{"id":"9","title":"September","path":"/month/9/"},"day":{"id":"12","ordinal":"th"}},"movie":{"id":"tt0018578","path":"/tt0018578/","title":"Wings","year":1927}},{"id":"11-11-tt0020629","title":"","dayofyear":{"path":"/11/11/","month":{"id":"11","title":"November","path":"/month/11/"},"day":{"id":"11","ordinal":"th"}},"movie":{"id":"tt0020629","path":"/tt0020629/","title":"All Quiet on the Western Front","year":1930}},{"id":"1-30-tt0352277","title":"Cole Porter and Linda Thomas marry","dayofyear":{"path":"/1/30/","month":{"id":"1","title":"January","path":"/month/1/"},"day":{"id":"30","ordinal":"th"}},"movie":{"id":"tt0352277","path":"/tt0352277/","title":"De-Lovely","year":2004}}]}},"context":{}}