{"hash":"53f4a1fd350e667bff2ab3c22ecc959ee66069f5","data":{"year":{"title":1831,"events":[{"id":"8-17-tt0025004","title":"Edmond Dantès escapes from Château d'If","dayofyear":{"path":"/august/17/","month":{"id":"august","title":"August","path":"/august/"},"day":{"id":"17","ordinal":"th"}},"movie":{"id":"tt0025004","path":"/movie/tt0025004/","title":"The Count of Monte Cristo","year":{"id":"1934","path":"/released/1934/"}}},{"id":"8-21-tt4196450","title":"Nat Turner begins his rebellion","dayofyear":{"path":"/august/21/","month":{"id":"august","title":"August","path":"/august/"},"day":{"id":"21","ordinal":"st"}},"movie":{"id":"tt4196450","path":"/movie/tt4196450/","title":"The Birth of a Nation","year":{"id":"2016","path":"/released/2016/"}}},{"id":"11-11-tt4196450","title":"Nat Turner is hanged","dayofyear":{"path":"/november/11/","month":{"id":"november","title":"November","path":"/november/"},"day":{"id":"11","ordinal":"th"}},"movie":{"id":"tt4196450","path":"/movie/tt4196450/","title":"The Birth of a Nation","year":{"id":"2016","path":"/released/2016/"}}}]}},"context":{}}