{
	"name": "Rocky",
	"tmdb_id": "1366",
	"imdb_id": "tt0075148",
	"hdmovielogo": [
		{
			"id": "83812",
			"url": "https://assets.fanart.tv/fanart/movies/1366/hdmovielogo/rocky-541f719e46b44.png",
			"lang": "en",
			"likes": "30"
		},
		{
			"id": "55951",
			"url": "https://assets.fanart.tv/fanart/movies/1366/hdmovielogo/rocky-5277964fcd8a9.png",
			"lang": "en",
			"likes": "30"
		},
		{
			"id": "71086",
			"url": "https://assets.fanart.tv/fanart/movies/1366/hdmovielogo/rocky-5362a7bef1822.png",
			"lang": "en",
			"likes": "26"
		},
		{
			"id": "154141",
			"url": "https://assets.fanart.tv/fanart/movies/1366/hdmovielogo/rocky-57485c27cbb05.png",
			"lang": "en",
			"likes": "25"
		},
		{
			"id": "118592",
			"url": "https://assets.fanart.tv/fanart/movies/1366/hdmovielogo/rocky-55d5b6b396d6f.png",
			"lang": "en",
			"likes": "25"
		},
		{
			"id": "13798",
			"url": "https://assets.fanart.tv/fanart/movies/1366/hdmovielogo/rocky-50560a877007a.png",
			"lang": "en",
			"likes": "25"
		},
		{
			"id": "70339",
			"url": "https://assets.fanart.tv/fanart/movies/1366/hdmovielogo/rocky-53556216d73a2.png",
			"lang": "en",
			"likes": "24"
		},
		{
			"id": "207647",
			"url": "https://assets.fanart.tv/fanart/movies/1366/hdmovielogo/rocky-59e6af2846525.png",
			"lang": "en",
			"likes": "20"
		}
	],
	"hdmovieclearart": [
		{
			"id": "83813",
			"url": "https://assets.fanart.tv/fanart/movies/1366/hdmovieclearart/rocky-541f71f141ecf.png",
			"lang": "en",
			"likes": "29"
		},
		{
			"id": "183378",
			"url": "https://assets.fanart.tv/fanart/movies/1366/hdmovieclearart/rocky-58a47f0c8c8e3.png",
			"lang": "en",
			"likes": "19"
		},
		{
			"id": "216873",
			"url": "https://assets.fanart.tv/fanart/movies/1366/hdmovieclearart/rocky-5a6fa9eb640c7.png",
			"lang": "en",
			"likes": "18"
		}
	],
	"moviedisc": [
		{
			"id": "70253",
			"url": "https://assets.fanart.tv/fanart/movies/1366/moviedisc/rocky-535385a804e7f.png",
			"lang": "en",
			"likes": "29",
			"disc": "1",
			"disc_type": "bluray"
		},
		{
			"id": "56038",
			"url": "https://assets.fanart.tv/fanart/movies/1366/moviedisc/rocky-52797bf9dca66.png",
			"lang": "en",
			"likes": "28",
			"disc": "1",
			"disc_type": "bluray"
		},
		{
			"id": "71173",
			"url": "https://assets.fanart.tv/fanart/movies/1366/moviedisc/rocky-53649bf4ecf0d.png",
			"lang": "en",
			"likes": "27",
			"disc": "1",
			"disc_type": "bluray"
		},
		{
			"id": "144205",
			"url": "https://assets.fanart.tv/fanart/movies/1366/moviedisc/rocky-56ef3ff1313f7.png",
			"lang": "en",
			"likes": "27",
			"disc": "1",
			"disc_type": "bluray"
		},
		{
			"id": "143829",
			"url": "https://assets.fanart.tv/fanart/movies/1366/moviedisc/rocky-56ecb077e49ef.png",
			"lang": "en",
			"likes": "26",
			"disc": "1",
			"disc_type": "bluray"
		},
		{
			"id": "3348",
			"url": "https://assets.fanart.tv/fanart/movies/1366/moviedisc/rocky-4fa6178c5b5ae.png",
			"lang": "en",
			"likes": "25",
			"disc": "1",
			"disc_type": "bluray"
		},
		{
			"id": "827",
			"url": "https://assets.fanart.tv/fanart/movies/1366/moviedisc/rocky-4f5fb1b1d965f.png",
			"lang": "de",
			"likes": "24",
			"disc": "1",
			"disc_type": "bluray"
		},
		{
			"id": "2715",
			"url": "https://assets.fanart.tv/fanart/movies/1366/moviedisc/rocky-4f927e8fc0158.png",
			"lang": "en",
			"likes": "24",
			"disc": "1",
			"disc_type": "dvd"
		},
		{
			"id": "223747",
			"url": "https://assets.fanart.tv/fanart/movies/1366/moviedisc/rocky-5ac8b01a3b08a.png",
			"lang": "en",
			"likes": "21",
			"disc": "1",
			"disc_type": "bluray"
		},
		{
			"id": "183424",
			"url": "https://assets.fanart.tv/fanart/movies/1366/moviedisc/rocky-58a4ac43453ef.png",
			"lang": "en",
			"likes": "21",
			"disc": "1",
			"disc_type": "bluray"
		},
		{
			"id": "183425",
			"url": "https://assets.fanart.tv/fanart/movies/1366/moviedisc/rocky-58a4ac5c2ee07.png",
			"lang": "en",
			"likes": "20",
			"disc": "1",
			"disc_type": "bluray"
		},
		{
			"id": "244672",
			"url": "https://assets.fanart.tv/fanart/movies/1366/moviedisc/rocky-5c302f15dbb53.png",
			"lang": "en",
			"likes": "17",
			"disc": "1",
			"disc_type": "bluray"
		},
		{
			"id": "244673",
			"url": "https://assets.fanart.tv/fanart/movies/1366/moviedisc/rocky-5c302f15e6bc6.png",
			"lang": "en",
			"likes": "17",
			"disc": "1",
			"disc_type": "bluray"
		}
	],
	"movieposter": [
		{
			"id": "194432",
			"url": "https://assets.fanart.tv/fanart/movies/1366/movieposter/rocky-591b9d8d8f811.jpg",
			"lang": "en",
			"likes": "24"
		},
		{
			"id": "47726",
			"url": "https://assets.fanart.tv/fanart/movies/1366/movieposter/rocky-52198956448c8.jpg",
			"lang": "en",
			"likes": "23"
		},
		{
			"id": "194448",
			"url": "https://assets.fanart.tv/fanart/movies/1366/movieposter/rocky-591ba03d2017e.jpg",
			"lang": "en",
			"likes": "22"
		},
		{
			"id": "71081",
			"url": "https://assets.fanart.tv/fanart/movies/1366/movieposter/rocky-53629b05d1350.jpg",
			"lang": "en",
			"likes": "22"
		},
		{
			"id": "144152",
			"url": "https://assets.fanart.tv/fanart/movies/1366/movieposter/rocky-56eec85828673.jpg",
			"lang": "en",
			"likes": "21"
		},
		{
			"id": "194433",
			"url": "https://assets.fanart.tv/fanart/movies/1366/movieposter/rocky-591b9db415341.jpg",
			"lang": "00",
			"likes": "21"
		},
		{
			"id": "201834",
			"url": "https://assets.fanart.tv/fanart/movies/1366/movieposter/rocky-59881ff990d7d.jpg",
			"lang": "en",
			"likes": "20"
		},
		{
			"id": "225361",
			"url": "https://assets.fanart.tv/fanart/movies/1366/movieposter/rocky-5ae6673398721.jpg",
			"lang": "en",
			"likes": "19"
		},
		{
			"id": "250892",
			"url": "https://assets.fanart.tv/fanart/movies/1366/movieposter/rocky-5c87b0fa1f673.jpg",
			"lang": "en",
			"likes": "18"
		},
		{
			"id": "125152",
			"url": "https://assets.fanart.tv/fanart/movies/1366/movieposter/rocky-562416f2aea28.jpg",
			"lang": "en",
			"likes": "17"
		},
		{
			"id": "249933",
			"url": "https://assets.fanart.tv/fanart/movies/1366/movieposter/rocky-5c7d65f1e9d54.jpg",
			"lang": "en",
			"likes": "16"
		},
		{
			"id": "47690",
			"url": "https://assets.fanart.tv/fanart/movies/1366/movieposter/rocky-5219518dabfc0.jpg",
			"lang": "en",
			"likes": "12"
		},
		{
			"id": "280558",
			"url": "https://assets.fanart.tv/fanart/movies/1366/movieposter/rocky-5df22f91937a4.jpg",
			"lang": "en",
			"likes": "12"
		},
		{
			"id": "236958",
			"url": "https://assets.fanart.tv/fanart/movies/1366/movieposter/rocky-5bb0f0c32450c.jpg",
			"lang": "00",
			"likes": "10"
		}
	],
	"moviebanner": [
		{
			"id": "180243",
			"url": "https://assets.fanart.tv/fanart/movies/1366/moviebanner/rocky-5886298be782a.jpg",
			"lang": "en",
			"likes": "23"
		},
		{
			"id": "183364",
			"url": "https://assets.fanart.tv/fanart/movies/1366/moviebanner/rocky-58a478db1a37b.jpg",
			"lang": "en",
			"likes": "23"
		},
		{
			"id": "48714",
			"url": "https://assets.fanart.tv/fanart/movies/1366/moviebanner/rocky-5222ae3726251.jpg",
			"lang": "en",
			"likes": "22"
		},
		{
			"id": "234160",
			"url": "https://assets.fanart.tv/fanart/movies/1366/moviebanner/rocky-5b8129d121b15.jpg",
			"lang": "en",
			"likes": "16"
		}
	],
	"moviethumb": [
		{
			"id": "180244",
			"url": "https://assets.fanart.tv/fanart/movies/1366/moviethumb/rocky-5886299720cc7.jpg",
			"lang": "en",
			"likes": "23"
		},
		{
			"id": "48715",
			"url": "https://assets.fanart.tv/fanart/movies/1366/moviethumb/rocky-5222ae3ee56f8.jpg",
			"lang": "en",
			"likes": "22"
		},
		{
			"id": "183376",
			"url": "https://assets.fanart.tv/fanart/movies/1366/moviethumb/rocky-58a47ae9daec7.jpg",
			"lang": "en",
			"likes": "22"
		},
		{
			"id": "279494",
			"url": "https://assets.fanart.tv/fanart/movies/1366/moviethumb/rocky-5de56890394c0.jpg",
			"lang": "en",
			"likes": "13"
		},
		{
			"id": "295641",
			"url": "https://assets.fanart.tv/fanart/movies/1366/moviethumb/rocky-5e984bf9121df.jpg",
			"lang": "en",
			"likes": "12"
		}
	],
	"movielogo": [
		{
			"id": "4910",
			"url": "https://assets.fanart.tv/fanart/movies/1366/movielogo/rocky-4fd38d2b55d23.png",
			"lang": "en",
			"likes": "23"
		}
	],
	"moviebackground": [
		{
			"id": "194434",
			"url": "https://assets.fanart.tv/fanart/movies/1366/moviebackground/rocky-591b9dd69d6f4.jpg",
			"lang": "",
			"likes": "23"
		},
		{
			"id": "255210",
			"url": "https://assets.fanart.tv/fanart/movies/1366/moviebackground/rocky-5cbd856fa6076.jpg",
			"lang": "",
			"likes": "18"
		},
		{
			"id": "141768",
			"url": "https://assets.fanart.tv/fanart/movies/1366/moviebackground/rocky-56dbc990485be.jpg",
			"lang": "",
			"likes": "17"
		},
		{
			"id": "144168",
			"url": "https://assets.fanart.tv/fanart/movies/1366/moviebackground/rocky-56eee3cfa0b9e.jpg",
			"lang": "",
			"likes": "16"
		},
		{
			"id": "254453",
			"url": "https://assets.fanart.tv/fanart/movies/1366/moviebackground/rocky-5cb3b8342169f.jpg",
			"lang": "",
			"likes": "16"
		},
		{
			"id": "83911",
			"url": "https://assets.fanart.tv/fanart/movies/1366/moviebackground/rocky-5420419b468e9.jpg",
			"lang": "",
			"likes": "9"
		},
		{
			"id": "83912",
			"url": "https://assets.fanart.tv/fanart/movies/1366/moviebackground/rocky-5420419b471ab.jpg",
			"lang": "",
			"likes": "9"
		},
		{
			"id": "295642",
			"url": "https://assets.fanart.tv/fanart/movies/1366/moviebackground/rocky-5e984f906f323.jpg",
			"lang": "",
			"likes": "9"
		},
		{
			"id": "83938",
			"url": "https://assets.fanart.tv/fanart/movies/1366/moviebackground/rocky-542058bb33bb9.jpg",
			"lang": "",
			"likes": "9"
		}
	]
}