{
	"title": "Cinco de Mayo, La Batalla",
	"_year_data": "2013",
	"year": 2013,
	"rated": "R",
	"released": "2013-05-02T12:00:00.000Z",
	"runtime": "125 min",
	"genres": "Drama, History, War",
	"director": "Rafa Lara",
	"writer": "Rafa Lara",
	"actors": "Christian Vazquez, Kuno Becker, Liz Gallardo, William Miller",
	"plot": "On May 5th, 1862, a few thousand Mexican soldiers put their lives on the line against the world's largest and most powerful army in one legendary battle for freedom and for Mexico.",
	"languages": "Spanish, French, English",
	"country": "Mexico",
	"awards": "3 wins & 1 nomination.",
	"poster": "https://m.media-amazon.com/images/M/MV5BMjAzMjg4MDU1OF5BMl5BanBnXkFtZTcwNjg4MDU0OQ@@._V1_SX300.jpg",
	"ratings": [
		{
			"Source": "Internet Movie Database",
			"Value": "6.2/10"
		}
	],
	"metascore": "N/A",
	"rating": 6.2,
	"votes": "810",
	"imdbid": "tt2553908",
	"type": "movie",
	"dvd": "N/A",
	"boxoffice": "N/A",
	"production": "Lionsgate",
	"website": "N/A",
	"response": "True",
	"name": "Cinco de Mayo, La Batalla",
	"series": false,
	"imdburl": "https://www.imdb.com/title/tt2553908"
}