{"hash":"f5d53563ac9fbdd58b69efcc87f522b4553f8e69","data":{"movie":{"id":"tt0054422","title":"The Last Days of Pompeii","plot":"Based on the Edward Bulwer-Lytton novel. Set in the shadows of Mt. Vesuvius just before its famous eruption, the film begins with Glaucus, a Roman legionnaire, returning to his home from far-off wars. Upon arriving, however, he discovers that his father has been murdered by a gang of black-hooded looting bandits. Glaucus vows revenge against the killers, but just how high up are those involved?","director":"Mario Bonnard","year":1959,"images":null,"studios":null,"genres":null,"countries":null,"languages":null}},"context":{}}